Workbook

Sheet Raw_Data
A1: Wallet Account Statement | E1: Date Printed | F1: 27 Dec 2025 22:27:55
A2: Account Name | B2: MUHAMMAD ABUBAKAR UMAR | C2: Account Number | D2: 8147735015 | E2: Address | F2: Danbare quarters, Opposite Buk gate, Ungogo, Ungogo, Kano
A3: Account Type | B3: Wallet Account | C3: Period | D3: 01 Jan 2025-26 Dec 2025
A4: Opening Balance | B4: ₦1,587.02 | C4: Total Debit | D4: ₦5,924,353.47 | E4: Debit Count | F4: 1505
A5: Closing Balance | B5: ₦6,318.86 | C5: Total Credit | D5: ₦5,929,085.31 | E5: Credit Count | F5: 377
A7: Trans. Date | B7: Value Date | C7: Description | D7: Debit(₦) | E7: Credit(₦) | F7: Balance After(₦) | G7: Channel | H7: Transaction Reference
A8: 01 Jan 2025 04:07:19 | B8: 01 Jan 2025 | C8: Airtime | 8147735015 | MTN | D8: 200.00 | E8: -- | F8: 1,387.02 | G8: Mobile | H8: 250101100100630513708890
A9: 01 Jan 2025 13:29:19 | B9: 01 Jan 2025 | C9: Transfer from KHAIRAT ZUBAIRU | OPay | 703****966 | D9: -- | E9: 300.00 | F9: 1,687.02 | G9: Mobile | H9: 250101010100635414096083
A10: 01 Jan 2025 14:00:41 | B10: 01 Jan 2025 | C10: Transfer to POS Transfer-AMINA HARUNA | MONIE POINT | 5730253158 | D10: 700.00 | E10: -- | F10: 987.02 | G10: Mobile | H10: 100004250101140046124766907091
A11: 01 Jan 2025 20:46:58 | B11: 01 Jan 2025 | C11: Transfer to POS Transfer-AMINA HARUNA | MONIE POINT | 5730253158 | D11: 500.00 | E11: -- | F11: 487.02 | G11: Mobile | H11: 100004250101204705124785870809
A12: 01 Jan 2025 20:51:11 | B12: 01 Jan 2025 | C12: Transfer to MUHAMMED OLUWATOBI ABDULSALAM | OPay | 9068533201 | D12: 100.00 | E12: -- | F12: 387.02 | G12: Mobile | H12: 250101010100640051465384
A13: 01 Jan 2025 22:10:30 | B13: 01 Jan 2025 | C13: Transfer from UMAR MUHAMMAD ABUBAKAR | Guaranty Trust Bank | 032****140 | NIP Transfer to MUHAMMAD ABUBAKAR UMAR. 000013250101231030000067145418 | D13: -- | E13: 9,900.00 | F13: 10,287.02 | G13: Mobile | H13: 000013250101231030000067145418
A14: 01 Jan 2025 22:11:06 | B14: 01 Jan 2025 | C14: Transfer from UMAR MUHAMMAD ABUBAKAR | Guaranty Trust Bank | 032****140 | NIP Transfer to MUHAMMAD ABUBAKAR UMAR. 000013250101231106000067145751 | D14: -- | E14: 5,000.00 | F14: 15,287.02 | G14: Mobile | H14: 000013250101231106000067145751
A15: 02 Jan 2025 07:33:21 | B15: 02 Jan 2025 | C15: Transfer to KHAIRAT ZUBAIRU | OPay | 7033715966 | D15: 2,000.00 | E15: -- | F15: 13,287.02 | G15: Mobile | H15: 250102010100642590690629
A16: 02 Jan 2025 07:40:54 | B16: 02 Jan 2025 | C16: Transfer to POS Transfer - IBRAHIM NAKOZI | MONIE POINT | 8173156921 | D16: 3,300.00 | E16: -- | F16: 9,987.02 | G16: Mobile | H16: 100004250102074100124792919479
A17: 02 Jan 2025 07:41:54 | B17: 02 Jan 2025 | C17: Transfer to POS Transfer - IBRAHIM NAKOZI | MONIE POINT | 8173156921 | D17: 500.00 | E17: -- | F17: 9,487.02 | G17: Mobile | H17: 100004250102074158124793509722
A18: 02 Jan 2025 08:03:00 | B18: 02 Jan 2025 | C18: Transfer to ABDULLAHI MUTTAKA | MONIE POINT | 9162038218 | D18: 100.00 | E18: -- | F18: 9,387.02 | G18: Mobile | H18: 100004250102080304124794033983
... A1889: 26 Dec 2025 20:45:17 | B1889: 26 Dec 2025 | C1889: Transfer to IBRAHIM ABDULWAHAB AHMAD | MONIE POINT | 8252517728 | D1889: 500.00 | E1889: -- | F1889: 6,318.86 | G1889: Mobile | H1889: 100004251226204521148583569147

Sheet Savings Account Transactions
A1: Savings Account Statement | E1: Date Printed | F1: 27 Dec 2025 22:27:55
A2: Account Name | B2: MUHAMMAD ABUBAKAR UMAR | C2: Account Number | D2: 8147735015 | E2: Address | F2: Danbare quarters, Opposite Buk gate, Ungogo, Ungogo, Kano
A3: Account Type | B3: Savings Account | C3: Period | D3: 01 Jan 2025-26 Dec 2025
A4: Opening Balance | B4: ₦0.00 | C4: Total Debit | D4: ₦62,064.81 | E4: Debit Count | F4: 28
A5: Closing Balance | B5: ₦0.00 | C5: Total Credit | D5: ₦62,064.81 | E5: Credit Count | F5: 21
A7: Trans. Date | B7: Value Date | C7: Description | D7: Debit(₦) | E7: Credit(₦) | F7: Balance After(₦) | G7: Channel | H7: Transaction Reference
A8: 27 Apr 2025 14:40:36 | B8: 27 Apr 2025 | C8: OWealth Deposit(from Fixed) | D8: -- | E8: 15,000.00 | F8: 15,000.00 | G8: Mobile | H8: 250427994bJBOx8QYPZQBowU0LzoOO
A9: 28 Apr 2025 10:36:30 | B9: 28 Apr 2025 | C9: OWealth Withdrawal(Transaction Payment) | D9: 1,000.00 | E9: -- | F9: 14,000.00 | G9: Mobile | H9: 250428010200418316863300
A10: 29 Apr 2025 02:54:23 | B10: 29 Apr 2025 | C10: OWealth Interest Earned | D10: -- | E10: 4.82 | F10: 14,004.82 | G10: Mobile | H10: 25042999afItiCioLpz2Fbu2GbxxW
A11: 29 Apr 2025 09:51:30 | B11: 29 Apr 2025 | C11: OWealth Withdrawal(Transaction Payment) | D11: 650.00 | E11: -- | F11: 13,354.82 | G11: Mobile | H11: 250429010200433677625903
A12: 29 Apr 2025 13:13:33 | B12: 29 Apr 2025 | C12: OWealth Withdrawal(Transaction Payment) | D12: 800.00 | E12: -- | F12: 12,554.82 | G12: Mobile | H12: 250429010200436547802803
A13: 29 Apr 2025 14:59:05 | B13: 29 Apr 2025 | C13: OWealth Withdrawal(Transaction Payment) | D13: 500.00 | E13: -- | F13: 12,054.82 | G13: Mobile | H13: 250429010200438096271443
A14: 29 Apr 2025 19:52:28 | B14: 29 Apr 2025 | C14: OWealth Withdrawal(Transaction Payment) | D14: 2,000.00 | E14: -- | F14: 10,054.82 | G14: Mobile | H14: 250429010200443587838646
A15: 30 Apr 2025 02:47:46 | B15: 30 Apr 2025 | C15: OWealth Interest Earned | D15: -- | E15: 3.46 | F15: 10,058.28 | G15: Mobile | H15: 250430993dixTLWiM7Zm8sLpBCYia7
A16: 01 May 2025 02:37:08 | B16: 01 May 2025 | C16: OWealth Interest Earned | D16: -- | E16: 3.46 | F16: 10,061.74 | G16: Mobile | H16: 2505019976yCp4VaDhItuINC2b6Tbg
A17: 01 May 2025 11:46:44 | B17: 01 May 2025 | C17: OWealth Withdrawal(Transaction Payment) | D17: 5,000.00 | E17: -- | F17: 5,061.74 | G17: Mobile | H17: 250501010200469848882800
A18: 01 May 2025 13:00:30 | B18: 01 May 2025 | C18: OWealth Deposit(from Fixed) | D18: -- | E18: 30,000.00 | F18: 35,061.74 | G18: Mobile | H18: 250501995ePRBNMXQwiK7BX9pNXzGQ
... A56: 26 Nov 2025 07:11:15 | B56: 26 Nov 2025 | C56: OWealth Withdrawal | D56: 5,001.71 | E56: -- | F56: 0.00 | G56: Mobile | H56: 251126010201854232706875

Sheet Cleaned_Data
A1: Date | B1: Month | C1: Month_number | D1: Transaction type | E1: Withdrawal | F1: Deposit | G1: Transaction_Direction | H1: Time of transaction | I1: Amount
A2: =Raw_Data!A8 -> 01 Jan 2025 04:07:19 | B2: =TEXT(A2,"MMMM") -> January | C2: =MONTH(A2) -> 1 | D2: =IFERROR(__xludf.DUMMYFUNCTION("IFERROR(IF(REGEXMATCH(LOWER(Raw_Data!C8),""fixed deposit|owealth|savings|target""),""Fixed Deposit"",IF(REGEXMATCH(LOWER(Raw_Data!C8),""airtime""),""Airtime"",IF(REGEXMATCH(LOWER(Raw_Data!C8),""electronic money transfer levy""),""Electronic Money Transfer"&" Levy"",IF(REGEXMATCH(LOWER(Raw_Data!C8),""transfer|trf|send""),""Transfer"",""Other"")))),""Other"")"),"Airtime") -> Airtime | E2: 200 | F2: 0 | G2: =IF(E2 <> 0,"Withdrawal","Deposit") -> Withdrawal | H2: =TEXT(Raw_Data!A8,"hh:mm:ss") -> 04:07:19 | I2: =IF(E2<> 0,E2,F2) -> 200
A3: =Raw_Data!A9 -> 01 Jan 2025 13:29:19 | B3: =TEXT(A3,"MMMM") -> January | C3: =MONTH(A3) -> 1 | D3: =IFERROR(__xludf.DUMMYFUNCTION("IFERROR(IF(REGEXMATCH(LOWER(Raw_Data!C9),""fixed deposit|owealth|savings|target""),""Fixed Deposit"",IF(REGEXMATCH(LOWER(Raw_Data!C9),""airtime""),""Airtime"",IF(REGEXMATCH(LOWER(Raw_Data!C9),""electronic money transfer levy""),""Electronic Money Transfer"&" Levy"",IF(REGEXMATCH(LOWER(Raw_Data!C9),""transfer|trf|send""),""Transfer"",""Other"")))),""Other"")"),"Transfer") -> Transfer | E3: 0 | F3: 300 | G3: =IF(E3 <> 0,"Withdrawal","Deposit") -> Deposit | H3: =TEXT(Raw_Data!A9,"hh:mm:ss") -> 13:29:19 | I3: =IF(E3<> 0,E3,F3) -> 300
A4: =Raw_Data!A10 -> 01 Jan 2025 14:00:41 | B4: =TEXT(A4,"MMMM") -> January | C4: =MONTH(A4) -> 1 | D4: =IFERROR(__xludf.DUMMYFUNCTION("IFERROR(IF(REGEXMATCH(LOWER(Raw_Data!C10),""fixed deposit|owealth|savings|target""),""Fixed Deposit"",IF(REGEXMATCH(LOWER(Raw_Data!C10),""airtime""),""Airtime"",IF(REGEXMATCH(LOWER(Raw_Data!C10),""electronic money transfer levy""),""Electronic Money Trans"&"fer Levy"",IF(REGEXMATCH(LOWER(Raw_Data!C10),""transfer|trf|send""),""Transfer"",""Other"")))),""Other"")"),"Transfer") -> Transfer | E4: 700 | F4: 0 | G4: =IF(E4 <> 0,"Withdrawal","Deposit") -> Withdrawal | H4: =TEXT(Raw_Data!A10,"hh:mm:ss") -> 14:00:41 | I4: =IF(E4<> 0,E4,F4) -> 700
A5: =Raw_Data!A11 -> 01 Jan 2025 20:46:58 | B5: =TEXT(A5,"MMMM") -> January | C5: =MONTH(A5) -> 1 | D5: =IFERROR(__xludf.DUMMYFUNCTION("IFERROR(IF(REGEXMATCH(LOWER(Raw_Data!C11),""fixed deposit|owealth|savings|target""),""Fixed Deposit"",IF(REGEXMATCH(LOWER(Raw_Data!C11),""airtime""),""Airtime"",IF(REGEXMATCH(LOWER(Raw_Data!C11),""electronic money transfer levy""),""Electronic Money Trans"&"fer Levy"",IF(REGEXMATCH(LOWER(Raw_Data!C11),""transfer|trf|send""),""Transfer"",""Other"")))),""Other"")"),"Transfer") -> Transfer | E5: 500 | F5: 0 | G5: =IF(E5 <> 0,"Withdrawal","Deposit") -> Withdrawal | H5: =TEXT(Raw_Data!A11,"hh:mm:ss") -> 20:46:58 | I5: =IF(E5<> 0,E5,F5) -> 500
A6: =Raw_Data!A12 -> 01 Jan 2025 20:51:11 | B6: =TEXT(A6,"MMMM") -> January | C6: =MONTH(A6) -> 1 | D6: =IFERROR(__xludf.DUMMYFUNCTION("IFERROR(IF(REGEXMATCH(LOWER(Raw_Data!C12),""fixed deposit|owealth|savings|target""),""Fixed Deposit"",IF(REGEXMATCH(LOWER(Raw_Data!C12),""airtime""),""Airtime"",IF(REGEXMATCH(LOWER(Raw_Data!C12),""electronic money transfer levy""),""Electronic Money Trans"&"fer Levy"",IF(REGEXMATCH(LOWER(Raw_Data!C12),""transfer|trf|send""),""Transfer"",""Other"")))),""Other"")"),"Transfer") -> Transfer | E6: 100 | F6: 0 | G6: =IF(E6 <> 0,"Withdrawal","Deposit") -> Withdrawal | H6: =TEXT(Raw_Data!A12,"hh:mm:ss") -> 20:51:11 | I6: =IF(E6<> 0,E6,F6) -> 100
A7: =Raw_Data!A13 -> 01 Jan 2025 22:10:30 | B7: =TEXT(A7,"MMMM") -> January | C7: =MONTH(A7) -> 1 | D7: =IFERROR(__xludf.DUMMYFUNCTION("IFERROR(IF(REGEXMATCH(LOWER(Raw_Data!C13),""fixed deposit|owealth|savings|target""),""Fixed Deposit"",IF(REGEXMATCH(LOWER(Raw_Data!C13),""airtime""),""Airtime"",IF(REGEXMATCH(LOWER(Raw_Data!C13),""electronic money transfer levy""),""Electronic Money Trans"&"fer Levy"",IF(REGEXMATCH(LOWER(Raw_Data!C13),""transfer|trf|send""),""Transfer"",""Other"")))),""Other"")"),"Transfer") -> Transfer | E7: 0 | F7: 9900 | G7: =IF(E7 <> 0,"Withdrawal","Deposit") -> Deposit | H7: =TEXT(Raw_Data!A13,"hh:mm:ss") -> 22:10:30 | I7: =IF(E7<> 0,E7,F7) -> 9900
A8: =Raw_Data!A14 -> 01 Jan 2025 22:11:06 | B8: =TEXT(A8,"MMMM") -> January | C8: =MONTH(A8) -> 1 | D8: =IFERROR(__xludf.DUMMYFUNCTION("IFERROR(IF(REGEXMATCH(LOWER(Raw_Data!C14),""fixed deposit|owealth|savings|target""),""Fixed Deposit"",IF(REGEXMATCH(LOWER(Raw_Data!C14),""airtime""),""Airtime"",IF(REGEXMATCH(LOWER(Raw_Data!C14),""electronic money transfer levy""),""Electronic Money Trans"&"fer Levy"",IF(REGEXMATCH(LOWER(Raw_Data!C14),""transfer|trf|send""),""Transfer"",""Other"")))),""Other"")"),"Transfer") -> Transfer | E8: 0 | F8: 5000 | G8: =IF(E8 <> 0,"Withdrawal","Deposit") -> Deposit | H8: =TEXT(Raw_Data!A14,"hh:mm:ss") -> 22:11:06 | I8: =IF(E8<> 0,E8,F8) -> 5000
A9: =Raw_Data!A15 -> 02 Jan 2025 07:33:21 | B9: =TEXT(A9,"MMMM") -> January | C9: =MONTH(A9) -> 1 | D9: =IFERROR(__xludf.DUMMYFUNCTION("IFERROR(IF(REGEXMATCH(LOWER(Raw_Data!C15),""fixed deposit|owealth|savings|target""),""Fixed Deposit"",IF(REGEXMATCH(LOWER(Raw_Data!C15),""airtime""),""Airtime"",IF(REGEXMATCH(LOWER(Raw_Data!C15),""electronic money transfer levy""),""Electronic Money Trans"&"fer Levy"",IF(REGEXMATCH(LOWER(Raw_Data!C15),""transfer|trf|send""),""Transfer"",""Other"")))),""Other"")"),"Transfer") -> Transfer | E9: 2000 | F9: 0 | G9: =IF(E9 <> 0,"Withdrawal","Deposit") -> Withdrawal | H9: =TEXT(Raw_Data!A15,"hh:mm:ss") -> 07:33:21 | I9: =IF(E9<> 0,E9,F9) -> 2000
A10: =Raw_Data!A16 -> 02 Jan 2025 07:40:54 | B10: =TEXT(A10,"MMMM") -> January | C10: =MONTH(A10) -> 1 | D10: =IFERROR(__xludf.DUMMYFUNCTION("IFERROR(IF(REGEXMATCH(LOWER(Raw_Data!C16),""fixed deposit|owealth|savings|target""),""Fixed Deposit"",IF(REGEXMATCH(LOWER(Raw_Data!C16),""airtime""),""Airtime"",IF(REGEXMATCH(LOWER(Raw_Data!C16),""electronic money transfer levy""),""Electronic Money Trans"&"fer Levy"",IF(REGEXMATCH(LOWER(Raw_Data!C16),""transfer|trf|send""),""Transfer"",""Other"")))),""Other"")"),"Transfer") -> Transfer | E10: 3300 | F10: 0 | G10: =IF(E10 <> 0,"Withdrawal","Deposit") -> Withdrawal | H10: =TEXT(Raw_Data!A16,"hh:mm:ss") -> 07:40:54 | I10: =IF(E10<> 0,E10,F10) -> 3300
A11: =Raw_Data!A17 -> 02 Jan 2025 07:41:54 | B11: =TEXT(A11,"MMMM") -> January | C11: =MONTH(A11) -> 1 | D11: =IFERROR(__xludf.DUMMYFUNCTION("IFERROR(IF(REGEXMATCH(LOWER(Raw_Data!C17),""fixed deposit|owealth|savings|target""),""Fixed Deposit"",IF(REGEXMATCH(LOWER(Raw_Data!C17),""airtime""),""Airtime"",IF(REGEXMATCH(LOWER(Raw_Data!C17),""electronic money transfer levy""),""Electronic Money Trans"&"fer Levy"",IF(REGEXMATCH(LOWER(Raw_Data!C17),""transfer|trf|send""),""Transfer"",""Other"")))),""Other"")"),"Transfer") -> Transfer | E11: 500 | F11: 0 | G11: =IF(E11 <> 0,"Withdrawal","Deposit") -> Withdrawal | H11: =TEXT(Raw_Data!A17,"hh:mm:ss") -> 07:41:54 | I11: =IF(E11<> 0,E11,F11) -> 500
A12: =Raw_Data!A18 -> 02 Jan 2025 08:03:00 | B12: =TEXT(A12,"MMMM") -> January | C12: =MONTH(A12) -> 1 | D12: =IFERROR(__xludf.DUMMYFUNCTION("IFERROR(IF(REGEXMATCH(LOWER(Raw_Data!C18),""fixed deposit|owealth|savings|target""),""Fixed Deposit"",IF(REGEXMATCH(LOWER(Raw_Data!C18),""airtime""),""Airtime"",IF(REGEXMATCH(LOWER(Raw_Data!C18),""electronic money transfer levy""),""Electronic Money Trans"&"fer Levy"",IF(REGEXMATCH(LOWER(Raw_Data!C18),""transfer|trf|send""),""Transfer"",""Other"")))),""Other"")"),"Transfer") -> Transfer | E12: 100 | F12: 0 | G12: =IF(E12 <> 0,"Withdrawal","Deposit") -> Withdrawal | H12: =TEXT(Raw_Data!A18,"hh:mm:ss") -> 08:03:00 | I12: =IF(E12<> 0,E12,F12) -> 100
A13: =Raw_Data!A19 -> 02 Jan 2025 12:16:34 | B13: =TEXT(A13,"MMMM") -> January | C13: =MONTH(A13) -> 1 | D13: =IFERROR(__xludf.DUMMYFUNCTION("IFERROR(IF(REGEXMATCH(LOWER(Raw_Data!C19),""fixed deposit|owealth|savings|target""),""Fixed Deposit"",IF(REGEXMATCH(LOWER(Raw_Data!C19),""airtime""),""Airtime"",IF(REGEXMATCH(LOWER(Raw_Data!C19),""electronic money transfer levy""),""Electronic Money Trans"&"fer Levy"",IF(REGEXMATCH(LOWER(Raw_Data!C19),""transfer|trf|send""),""Transfer"",""Other"")))),""Other"")"),"Transfer") -> Transfer | E13: 1410 | F13: 0 | G13: =IF(E13 <> 0,"Withdrawal","Deposit") -> Withdrawal | H13: =TEXT(Raw_Data!A19,"hh:mm:ss") -> 12:16:34 | I13: =IF(E13<> 0,E13,F13) -> 1410
A14: =Raw_Data!A20 -> 02 Jan 2025 16:19:54 | B14: =TEXT(A14,"MMMM") -> January | C14: =MONTH(A14) -> 1 | D14: =IFERROR(__xludf.DUMMYFUNCTION("IFERROR(IF(REGEXMATCH(LOWER(Raw_Data!C20),""fixed deposit|owealth|savings|target""),""Fixed Deposit"",IF(REGEXMATCH(LOWER(Raw_Data!C20),""airtime""),""Airtime"",IF(REGEXMATCH(LOWER(Raw_Data!C20),""electronic money transfer levy""),""Electronic Money Trans"&"fer Levy"",IF(REGEXMATCH(LOWER(Raw_Data!C20),""transfer|trf|send""),""Transfer"",""Other"")))),""Other"")"),"Transfer") -> Transfer | E14: 200 | F14: 0 | G14: =IF(E14 <> 0,"Withdrawal","Deposit") -> Withdrawal | H14: =TEXT(Raw_Data!A20,"hh:mm:ss") -> 16:19:54 | I14: =IF(E14<> 0,E14,F14) -> 200
A15: =Raw_Data!A21 -> 02 Jan 2025 20:04:55 | B15: =TEXT(A15,"MMMM") -> January | C15: =MONTH(A15) -> 1 | D15: =IFERROR(__xludf.DUMMYFUNCTION("IFERROR(IF(REGEXMATCH(LOWER(Raw_Data!C21),""fixed deposit|owealth|savings|target""),""Fixed Deposit"",IF(REGEXMATCH(LOWER(Raw_Data!C21),""airtime""),""Airtime"",IF(REGEXMATCH(LOWER(Raw_Data!C21),""electronic money transfer levy""),""Electronic Money Trans"&"fer Levy"",IF(REGEXMATCH(LOWER(Raw_Data!C21),""transfer|trf|send""),""Transfer"",""Other"")))),""Other"")"),"Transfer") -> Transfer | E15: 0 | F15: 1000 | G15: =IF(E15 <> 0,"Withdrawal","Deposit") -> Deposit | H15: =TEXT(Raw_Data!A21,"hh:mm:ss") -> 20:04:55 | I15: =IF(E15<> 0,E15,F15) -> 1000
A16: =Raw_Data!A22 -> 02 Jan 2025 20:17:14 | B16: =TEXT(A16,"MMMM") -> January | C16: =MONTH(A16) -> 1 | D16: =IFERROR(__xludf.DUMMYFUNCTION("IFERROR(IF(REGEXMATCH(LOWER(Raw_Data!C22),""fixed deposit|owealth|savings|target""),""Fixed Deposit"",IF(REGEXMATCH(LOWER(Raw_Data!C22),""airtime""),""Airtime"",IF(REGEXMATCH(LOWER(Raw_Data!C22),""electronic money transfer levy""),""Electronic Money Trans"&"fer Levy"",IF(REGEXMATCH(LOWER(Raw_Data!C22),""transfer|trf|send""),""Transfer"",""Other"")))),""Other"")"),"Transfer") -> Transfer | E16: 2110 | F16: 0 | G16: =IF(E16 <> 0,"Withdrawal","Deposit") -> Withdrawal | H16: =TEXT(Raw_Data!A22,"hh:mm:ss") -> 20:17:14 | I16: =IF(E16<> 0,E16,F16) -> 2110
A17: =Raw_Data!A23 -> 03 Jan 2025 09:44:30 | B17: =TEXT(A17,"MMMM") -> January | C17: =MONTH(A17) -> 1 | D17: =IFERROR(__xludf.DUMMYFUNCTION("IFERROR(IF(REGEXMATCH(LOWER(Raw_Data!C23),""fixed deposit|owealth|savings|target""),""Fixed Deposit"",IF(REGEXMATCH(LOWER(Raw_Data!C23),""airtime""),""Airtime"",IF(REGEXMATCH(LOWER(Raw_Data!C23),""electronic money transfer levy""),""Electronic Money Trans"&"fer Levy"",IF(REGEXMATCH(LOWER(Raw_Data!C23),""transfer|trf|send""),""Transfer"",""Other"")))),""Other"")"),"Transfer") -> Transfer | E17: 1050 | F17: 0 | G17: =IF(E17 <> 0,"Withdrawal","Deposit") -> Withdrawal | H17: =TEXT(Raw_Data!A23,"hh:mm:ss") -> 09:44:30 | I17: =IF(E17<> 0,E17,F17) -> 1050
A18: =Raw_Data!A24 -> 03 Jan 2025 11:02:53 | B18: =TEXT(A18,"MMMM") -> January | C18: =MONTH(A18) -> 1 | D18: =IFERROR(__xludf.DUMMYFUNCTION("IFERROR(IF(REGEXMATCH(LOWER(Raw_Data!C24),""fixed deposit|owealth|savings|target""),""Fixed Deposit"",IF(REGEXMATCH(LOWER(Raw_Data!C24),""airtime""),""Airtime"",IF(REGEXMATCH(LOWER(Raw_Data!C24),""electronic money transfer levy""),""Electronic Money Trans"&"fer Levy"",IF(REGEXMATCH(LOWER(Raw_Data!C24),""transfer|trf|send""),""Transfer"",""Other"")))),""Other"")"),"Airtime") -> Airtime | E18: 200 | F18: 0 | G18: =IF(E18 <> 0,"Withdrawal","Deposit") -> Withdrawal | H18: =TEXT(Raw_Data!A24,"hh:mm:ss") -> 11:02:53 | I18: =IF(E18<> 0,E18,F18) -> 200
A19: =Raw_Data!A25 -> 03 Jan 2025 11:29:36 | B19: =TEXT(A19,"MMMM") -> January | C19: =MONTH(A19) -> 1 | D19: =IFERROR(__xludf.DUMMYFUNCTION("IFERROR(IF(REGEXMATCH(LOWER(Raw_Data!C25),""fixed deposit|owealth|savings|target""),""Fixed Deposit"",IF(REGEXMATCH(LOWER(Raw_Data!C25),""airtime""),""Airtime"",IF(REGEXMATCH(LOWER(Raw_Data!C25),""electronic money transfer levy""),""Electronic Money Trans"&"fer Levy"",IF(REGEXMATCH(LOWER(Raw_Data!C25),""transfer|trf|send""),""Transfer"",""Other"")))),""Other"")"),"Transfer") -> Transfer | E19: 1000 | F19: 0 | G19: =IF(E19 <> 0,"Withdrawal","Deposit") -> Withdrawal | H19: =TEXT(Raw_Data!A25,"hh:mm:ss") -> 11:29:36 | I19: =IF(E19<> 0,E19,F19) -> 1000
A20: =Raw_Data!A26 -> 03 Jan 2025 12:55:56 | B20: =TEXT(A20,"MMMM") -> January | C20: =MONTH(A20) -> 1 | D20: =IFERROR(__xludf.DUMMYFUNCTION("IFERROR(IF(REGEXMATCH(LOWER(Raw_Data!C26),""fixed deposit|owealth|savings|target""),""Fixed Deposit"",IF(REGEXMATCH(LOWER(Raw_Data!C26),""airtime""),""Airtime"",IF(REGEXMATCH(LOWER(Raw_Data!C26),""electronic money transfer levy""),""Electronic Money Trans"&"fer Levy"",IF(REGEXMATCH(LOWER(Raw_Data!C26),""transfer|trf|send""),""Transfer"",""Other"")))),""Other"")"),"Transfer") -> Transfer | E20: 250 | F20: 0 | G20: =IF(E20 <> 0,"Withdrawal","Deposit") -> Withdrawal | H20: =TEXT(Raw_Data!A26,"hh:mm:ss") -> 12:55:56 | I20: =IF(E20<> 0,E20,F20) -> 250
A21: =Raw_Data!A27 -> 03 Jan 2025 16:09:32 | B21: =TEXT(A21,"MMMM") -> January | C21: =MONTH(A21) -> 1 | D21: =IFERROR(__xludf.DUMMYFUNCTION("IFERROR(IF(REGEXMATCH(LOWER(Raw_Data!C27),""fixed deposit|owealth|savings|target""),""Fixed Deposit"",IF(REGEXMATCH(LOWER(Raw_Data!C27),""airtime""),""Airtime"",IF(REGEXMATCH(LOWER(Raw_Data!C27),""electronic money transfer levy""),""Electronic Money Trans"&"fer Levy"",IF(REGEXMATCH(LOWER(Raw_Data!C27),""transfer|trf|send""),""Transfer"",""Other"")))),""Other"")"),"Transfer") -> Transfer | E21: 600 | F21: 0 | G21: =IF(E21 <> 0,"Withdrawal","Deposit") -> Withdrawal | H21: =TEXT(Raw_Data!A27,"hh:mm:ss") -> 16:09:32 | I21: =IF(E21<> 0,E21,F21) -> 600
A22: =Raw_Data!A28 -> 03 Jan 2025 23:32:01 | B22: =TEXT(A22,"MMMM") -> January | C22: =MONTH(A22) -> 1 | D22: =IFERROR(__xludf.DUMMYFUNCTION("IFERROR(IF(REGEXMATCH(LOWER(Raw_Data!C28),""fixed deposit|owealth|savings|target""),""Fixed Deposit"",IF(REGEXMATCH(LOWER(Raw_Data!C28),""airtime""),""Airtime"",IF(REGEXMATCH(LOWER(Raw_Data!C28),""electronic money transfer levy""),""Electronic Money Trans"&"fer Levy"",IF(REGEXMATCH(LOWER(Raw_Data!C28),""transfer|trf|send""),""Transfer"",""Other"")))),""Other"")"),"Transfer") -> Transfer | E22: 0 | F22: 9999 | G22: =IF(E22 <> 0,"Withdrawal","Deposit") -> Deposit | H22: =TEXT(Raw_Data!A28,"hh:mm:ss") -> 23:32:01 | I22: =IF(E22<> 0,E22,F22) -> 9999
A23: =Raw_Data!A29 -> 03 Jan 2025 23:32:22 | B23: =TEXT(A23,"MMMM") -> January | C23: =MONTH(A23) -> 1 | D23: =IFERROR(__xludf.DUMMYFUNCTION("IFERROR(IF(REGEXMATCH(LOWER(Raw_Data!C29),""fixed deposit|owealth|savings|target""),""Fixed Deposit"",IF(REGEXMATCH(LOWER(Raw_Data!C29),""airtime""),""Airtime"",IF(REGEXMATCH(LOWER(Raw_Data!C29),""electronic money transfer levy""),""Electronic Money Trans"&"fer Levy"",IF(REGEXMATCH(LOWER(Raw_Data!C29),""transfer|trf|send""),""Transfer"",""Other"")))),""Other"")"),"Transfer") -> Transfer | E23: 0 | F23: 5001 | G23: =IF(E23 <> 0,"Withdrawal","Deposit") -> Deposit | H23: =TEXT(Raw_Data!A29,"hh:mm:ss") -> 23:32:22 | I23: =IF(E23<> 0,E23,F23) -> 5001
A24: =Raw_Data!A30 -> 03 Jan 2025 23:35:03 | B24: =TEXT(A24,"MMMM") -> January | C24: =MONTH(A24) -> 1 | D24: =IFERROR(__xludf.DUMMYFUNCTION("IFERROR(IF(REGEXMATCH(LOWER(Raw_Data!C30),""fixed deposit|owealth|savings|target""),""Fixed Deposit"",IF(REGEXMATCH(LOWER(Raw_Data!C30),""airtime""),""Airtime"",IF(REGEXMATCH(LOWER(Raw_Data!C30),""electronic money transfer levy""),""Electronic Money Trans"&"fer Levy"",IF(REGEXMATCH(LOWER(Raw_Data!C30),""transfer|trf|send""),""Transfer"",""Other"")))),""Other"")"),"Transfer") -> Transfer | E24: 12000 | F24: 0 | G24: =IF(E24 <> 0,"Withdrawal","Deposit") -> Withdrawal | H24: =TEXT(Raw_Data!A30,"hh:mm:ss") -> 23:35:03 | I24: =IF(E24<> 0,E24,F24) -> 12000
A25: =Raw_Data!A31 -> 04 Jan 2025 08:19:48 | B25: =TEXT(A25,"MMMM") -> January | C25: =MONTH(A25) -> 1 | D25: =IFERROR(__xludf.DUMMYFUNCTION("IFERROR(IF(REGEXMATCH(LOWER(Raw_Data!C31),""fixed deposit|owealth|savings|target""),""Fixed Deposit"",IF(REGEXMATCH(LOWER(Raw_Data!C31),""airtime""),""Airtime"",IF(REGEXMATCH(LOWER(Raw_Data!C31),""electronic money transfer levy""),""Electronic Money Trans"&"fer Levy"",IF(REGEXMATCH(LOWER(Raw_Data!C31),""transfer|trf|send""),""Transfer"",""Other"")))),""Other"")"),"Transfer") -> Transfer | E25: 300 | F25: 0 | G25: =IF(E25 <> 0,"Withdrawal","Deposit") -> Withdrawal | H25: =TEXT(Raw_Data!A31,"hh:mm:ss") -> 08:19:48 | I25: =IF(E25<> 0,E25,F25) -> 300
A26: =Raw_Data!A32 -> 04 Jan 2025 09:16:10 | B26: =TEXT(A26,"MMMM") -> January | C26: =MONTH(A26) -> 1 | D26: =IFERROR(__xludf.DUMMYFUNCTION("IFERROR(IF(REGEXMATCH(LOWER(Raw_Data!C32),""fixed deposit|owealth|savings|target""),""Fixed Deposit"",IF(REGEXMATCH(LOWER(Raw_Data!C32),""airtime""),""Airtime"",IF(REGEXMATCH(LOWER(Raw_Data!C32),""electronic money transfer levy""),""Electronic Money Trans"&"fer Levy"",IF(REGEXMATCH(LOWER(Raw_Data!C32),""transfer|trf|send""),""Transfer"",""Other"")))),""Other"")"),"Transfer") -> Transfer | E26: 0 | F26: 300 | G26: =IF(E26 <> 0,"Withdrawal","Deposit") -> Deposit | H26: =TEXT(Raw_Data!A32,"hh:mm:ss") -> 09:16:10 | I26: =IF(E26<> 0,E26,F26) -> 300
A27: =Raw_Data!A33 -> 04 Jan 2025 09:38:25 | B27: =TEXT(A27,"MMMM") -> January | C27: =MONTH(A27) -> 1 | D27: =IFERROR(__xludf.DUMMYFUNCTION("IFERROR(IF(REGEXMATCH(LOWER(Raw_Data!C33),""fixed deposit|owealth|savings|target""),""Fixed Deposit"",IF(REGEXMATCH(LOWER(Raw_Data!C33),""airtime""),""Airtime"",IF(REGEXMATCH(LOWER(Raw_Data!C33),""electronic money transfer levy""),""Electronic Money Trans"&"fer Levy"",IF(REGEXMATCH(LOWER(Raw_Data!C33),""transfer|trf|send""),""Transfer"",""Other"")))),""Other"")"),"Transfer") -> Transfer | E27: 2150 | F27: 0 | G27: =IF(E27 <> 0,"Withdrawal","Deposit") -> Withdrawal | H27: =TEXT(Raw_Data!A33,"hh:mm:ss") -> 09:38:25 | I27: =IF(E27<> 0,E27,F27) -> 2150
A28: =Raw_Data!A34 -> 04 Jan 2025 09:43:27 | B28: =TEXT(A28,"MMMM") -> January | C28: =MONTH(A28) -> 1 | D28: =IFERROR(__xludf.DUMMYFUNCTION("IFERROR(IF(REGEXMATCH(LOWER(Raw_Data!C34),""fixed deposit|owealth|savings|target""),""Fixed Deposit"",IF(REGEXMATCH(LOWER(Raw_Data!C34),""airtime""),""Airtime"",IF(REGEXMATCH(LOWER(Raw_Data!C34),""electronic money transfer levy""),""Electronic Money Trans"&"fer Levy"",IF(REGEXMATCH(LOWER(Raw_Data!C34),""transfer|trf|send""),""Transfer"",""Other"")))),""Other"")"),"Transfer") -> Transfer | E28: 1820 | F28: 0 | G28: =IF(E28 <> 0,"Withdrawal","Deposit") -> Withdrawal | H28: =TEXT(Raw_Data!A34,"hh:mm:ss") -> 09:43:27 | I28: =IF(E28<> 0,E28,F28) -> 1820
A29: =Raw_Data!A35 -> 04 Jan 2025 11:33:54 | B29: =TEXT(A29,"MMMM") -> January | C29: =MONTH(A29) -> 1 | D29: =IFERROR(__xludf.DUMMYFUNCTION("IFERROR(IF(REGEXMATCH(LOWER(Raw_Data!C35),""fixed deposit|owealth|savings|target""),""Fixed Deposit"",IF(REGEXMATCH(LOWER(Raw_Data!C35),""airtime""),""Airtime"",IF(REGEXMATCH(LOWER(Raw_Data!C35),""electronic money transfer levy""),""Electronic Money Trans"&"fer Levy"",IF(REGEXMATCH(LOWER(Raw_Data!C35),""transfer|trf|send""),""Transfer"",""Other"")))),""Other"")"),"Airtime") -> Airtime | E29: 500 | F29: 0 | G29: =IF(E29 <> 0,"Withdrawal","Deposit") -> Withdrawal | H29: =TEXT(Raw_Data!A35,"hh:mm:ss") -> 11:33:54 | I29: =IF(E29<> 0,E29,F29) -> 500
A30: =Raw_Data!A36 -> 04 Jan 2025 15:28:50 | B30: =TEXT(A30,"MMMM") -> January | C30: =MONTH(A30) -> 1 | D30: =IFERROR(__xludf.DUMMYFUNCTION("IFERROR(IF(REGEXMATCH(LOWER(Raw_Data!C36),""fixed deposit|owealth|savings|target""),""Fixed Deposit"",IF(REGEXMATCH(LOWER(Raw_Data!C36),""airtime""),""Airtime"",IF(REGEXMATCH(LOWER(Raw_Data!C36),""electronic money transfer levy""),""Electronic Money Trans"&"fer Levy"",IF(REGEXMATCH(LOWER(Raw_Data!C36),""transfer|trf|send""),""Transfer"",""Other"")))),""Other"")"),"Transfer") -> Transfer | E30: 300 | F30: 0 | G30: =IF(E30 <> 0,"Withdrawal","Deposit") -> Withdrawal | H30: =TEXT(Raw_Data!A36,"hh:mm:ss") -> 15:28:50 | I30: =IF(E30<> 0,E30,F30) -> 300
A31: =Raw_Data!A37 -> 05 Jan 2025 11:21:19 | B31: =TEXT(A31,"MMMM") -> January | C31: =MONTH(A31) -> 1 | D31: =IFERROR(__xludf.DUMMYFUNCTION("IFERROR(IF(REGEXMATCH(LOWER(Raw_Data!C37),""fixed deposit|owealth|savings|target""),""Fixed Deposit"",IF(REGEXMATCH(LOWER(Raw_Data!C37),""airtime""),""Airtime"",IF(REGEXMATCH(LOWER(Raw_Data!C37),""electronic money transfer levy""),""Electronic Money Trans"&"fer Levy"",IF(REGEXMATCH(LOWER(Raw_Data!C37),""transfer|trf|send""),""Transfer"",""Other"")))),""Other"")"),"Transfer") -> Transfer | E31: 700 | F31: 0 | G31: =IF(E31 <> 0,"Withdrawal","Deposit") -> Withdrawal | H31: =TEXT(Raw_Data!A37,"hh:mm:ss") -> 11:21:19 | I31: =IF(E31<> 0,E31,F31) -> 700
A32: =Raw_Data!A38 -> 05 Jan 2025 18:44:12 | B32: =TEXT(A32,"MMMM") -> January | C32: =MONTH(A32) -> 1 | D32: =IFERROR(__xludf.DUMMYFUNCTION("IFERROR(IF(REGEXMATCH(LOWER(Raw_Data!C38),""fixed deposit|owealth|savings|target""),""Fixed Deposit"",IF(REGEXMATCH(LOWER(Raw_Data!C38),""airtime""),""Airtime"",IF(REGEXMATCH(LOWER(Raw_Data!C38),""electronic money transfer levy""),""Electronic Money Trans"&"fer Levy"",IF(REGEXMATCH(LOWER(Raw_Data!C38),""transfer|trf|send""),""Transfer"",""Other"")))),""Other"")"),"Transfer") -> Transfer | E32: 0 | F32: 5000 | G32: =IF(E32 <> 0,"Withdrawal","Deposit") -> Deposit | H32: =TEXT(Raw_Data!A38,"hh:mm:ss") -> 18:44:12 | I32: =IF(E32<> 0,E32,F32) -> 5000
A33: =Raw_Data!A39 -> 05 Jan 2025 19:02:58 | B33: =TEXT(A33,"MMMM") -> January | C33: =MONTH(A33) -> 1 | D33: =IFERROR(__xludf.DUMMYFUNCTION("IFERROR(IF(REGEXMATCH(LOWER(Raw_Data!C39),""fixed deposit|owealth|savings|target""),""Fixed Deposit"",IF(REGEXMATCH(LOWER(Raw_Data!C39),""airtime""),""Airtime"",IF(REGEXMATCH(LOWER(Raw_Data!C39),""electronic money transfer levy""),""Electronic Money Trans"&"fer Levy"",IF(REGEXMATCH(LOWER(Raw_Data!C39),""transfer|trf|send""),""Transfer"",""Other"")))),""Other"")"),"Transfer") -> Transfer | E33: 200 | F33: 0 | G33: =IF(E33 <> 0,"Withdrawal","Deposit") -> Withdrawal | H33: =TEXT(Raw_Data!A39,"hh:mm:ss") -> 19:02:58 | I33: =IF(E33<> 0,E33,F33) -> 200
A34: =Raw_Data!A40 -> 05 Jan 2025 19:08:44 | B34: =TEXT(A34,"MMMM") -> January | C34: =MONTH(A34) -> 1 | D34: =IFERROR(__xludf.DUMMYFUNCTION("IFERROR(IF(REGEXMATCH(LOWER(Raw_Data!C40),""fixed deposit|owealth|savings|target""),""Fixed Deposit"",IF(REGEXMATCH(LOWER(Raw_Data!C40),""airtime""),""Airtime"",IF(REGEXMATCH(LOWER(Raw_Data!C40),""electronic money transfer levy""),""Electronic Money Trans"&"fer Levy"",IF(REGEXMATCH(LOWER(Raw_Data!C40),""transfer|trf|send""),""Transfer"",""Other"")))),""Other"")"),"Transfer") -> Transfer | E34: 1650 | F34: 0 | G34: =IF(E34 <> 0,"Withdrawal","Deposit") -> Withdrawal | H34: =TEXT(Raw_Data!A40,"hh:mm:ss") -> 19:08:44 | I34: =IF(E34<> 0,E34,F34) -> 1650
A35: =Raw_Data!A41 -> 05 Jan 2025 19:09:46 | B35: =TEXT(A35,"MMMM") -> January | C35: =MONTH(A35) -> 1 | D35: =IFERROR(__xludf.DUMMYFUNCTION("IFERROR(IF(REGEXMATCH(LOWER(Raw_Data!C41),""fixed deposit|owealth|savings|target""),""Fixed Deposit"",IF(REGEXMATCH(LOWER(Raw_Data!C41),""airtime""),""Airtime"",IF(REGEXMATCH(LOWER(Raw_Data!C41),""electronic money transfer levy""),""Electronic Money Trans"&"fer Levy"",IF(REGEXMATCH(LOWER(Raw_Data!C41),""transfer|trf|send""),""Transfer"",""Other"")))),""Other"")"),"Airtime") -> Airtime | E35: 500 | F35: 0 | G35: =IF(E35 <> 0,"Withdrawal","Deposit") -> Withdrawal | H35: =TEXT(Raw_Data!A41,"hh:mm:ss") -> 19:09:46 | I35: =IF(E35<> 0,E35,F35) -> 500
A36: =Raw_Data!A42 -> 05 Jan 2025 20:03:09 | B36: =TEXT(A36,"MMMM") -> January | C36: =MONTH(A36) -> 1 | D36: =IFERROR(__xludf.DUMMYFUNCTION("IFERROR(IF(REGEXMATCH(LOWER(Raw_Data!C42),""fixed deposit|owealth|savings|target""),""Fixed Deposit"",IF(REGEXMATCH(LOWER(Raw_Data!C42),""airtime""),""Airtime"",IF(REGEXMATCH(LOWER(Raw_Data!C42),""electronic money transfer levy""),""Electronic Money Trans"&"fer Levy"",IF(REGEXMATCH(LOWER(Raw_Data!C42),""transfer|trf|send""),""Transfer"",""Other"")))),""Other"")"),"Transfer") -> Transfer | E36: 900 | F36: 0 | G36: =IF(E36 <> 0,"Withdrawal","Deposit") -> Withdrawal | H36: =TEXT(Raw_Data!A42,"hh:mm:ss") -> 20:03:09 | I36: =IF(E36<> 0,E36,F36) -> 900
A37: =Raw_Data!A43 -> 06 Jan 2025 06:28:49 | B37: =TEXT(A37,"MMMM") -> January | C37: =MONTH(A37) -> 1 | D37: =IFERROR(__xludf.DUMMYFUNCTION("IFERROR(IF(REGEXMATCH(LOWER(Raw_Data!C43),""fixed deposit|owealth|savings|target""),""Fixed Deposit"",IF(REGEXMATCH(LOWER(Raw_Data!C43),""airtime""),""Airtime"",IF(REGEXMATCH(LOWER(Raw_Data!C43),""electronic money transfer levy""),""Electronic Money Trans"&"fer Levy"",IF(REGEXMATCH(LOWER(Raw_Data!C43),""transfer|trf|send""),""Transfer"",""Other"")))),""Other"")"),"Transfer") -> Transfer | E37: 0 | F37: 1500 | G37: =IF(E37 <> 0,"Withdrawal","Deposit") -> Deposit | H37: =TEXT(Raw_Data!A43,"hh:mm:ss") -> 06:28:49 | I37: =IF(E37<> 0,E37,F37) -> 1500
A38: =Raw_Data!A44 -> 06 Jan 2025 10:04:58 | B38: =TEXT(A38,"MMMM") -> January | C38: =MONTH(A38) -> 1 | D38: =IFERROR(__xludf.DUMMYFUNCTION("IFERROR(IF(REGEXMATCH(LOWER(Raw_Data!C44),""fixed deposit|owealth|savings|target""),""Fixed Deposit"",IF(REGEXMATCH(LOWER(Raw_Data!C44),""airtime""),""Airtime"",IF(REGEXMATCH(LOWER(Raw_Data!C44),""electronic money transfer levy""),""Electronic Money Trans"&"fer Levy"",IF(REGEXMATCH(LOWER(Raw_Data!C44),""transfer|trf|send""),""Transfer"",""Other"")))),""Other"")"),"Transfer") -> Transfer | E38: 200 | F38: 0 | G38: =IF(E38 <> 0,"Withdrawal","Deposit") -> Withdrawal | H38: =TEXT(Raw_Data!A44,"hh:mm:ss") -> 10:04:58 | I38: =IF(E38<> 0,E38,F38) -> 200
A39: =Raw_Data!A45 -> 06 Jan 2025 10:47:07 | B39: =TEXT(A39,"MMMM") -> January | C39: =MONTH(A39) -> 1 | D39: =IFERROR(__xludf.DUMMYFUNCTION("IFERROR(IF(REGEXMATCH(LOWER(Raw_Data!C45),""fixed deposit|owealth|savings|target""),""Fixed Deposit"",IF(REGEXMATCH(LOWER(Raw_Data!C45),""airtime""),""Airtime"",IF(REGEXMATCH(LOWER(Raw_Data!C45),""electronic money transfer levy""),""Electronic Money Trans"&"fer Levy"",IF(REGEXMATCH(LOWER(Raw_Data!C45),""transfer|trf|send""),""Transfer"",""Other"")))),""Other"")"),"Transfer") -> Transfer | E39: 2000 | F39: 0 | G39: =IF(E39 <> 0,"Withdrawal","Deposit") -> Withdrawal | H39: =TEXT(Raw_Data!A45,"hh:mm:ss") -> 10:47:07 | I39: =IF(E39<> 0,E39,F39) -> 2000
A40: =Raw_Data!A46 -> 06 Jan 2025 12:31:34 | B40: =TEXT(A40,"MMMM") -> January | C40: =MONTH(A40) -> 1 | D40: =IFERROR(__xludf.DUMMYFUNCTION("IFERROR(IF(REGEXMATCH(LOWER(Raw_Data!C46),""fixed deposit|owealth|savings|target""),""Fixed Deposit"",IF(REGEXMATCH(LOWER(Raw_Data!C46),""airtime""),""Airtime"",IF(REGEXMATCH(LOWER(Raw_Data!C46),""electronic money transfer levy""),""Electronic Money Trans"&"fer Levy"",IF(REGEXMATCH(LOWER(Raw_Data!C46),""transfer|trf|send""),""Transfer"",""Other"")))),""Other"")"),"Transfer") -> Transfer | E40: 200 | F40: 0 | G40: =IF(E40 <> 0,"Withdrawal","Deposit") -> Withdrawal | H40: =TEXT(Raw_Data!A46,"hh:mm:ss") -> 12:31:34 | I40: =IF(E40<> 0,E40,F40) -> 200
A41: =Raw_Data!A47 -> 06 Jan 2025 13:56:52 | B41: =TEXT(A41,"MMMM") -> January | C41: =MONTH(A41) -> 1 | D41: =IFERROR(__xludf.DUMMYFUNCTION("IFERROR(IF(REGEXMATCH(LOWER(Raw_Data!C47),""fixed deposit|owealth|savings|target""),""Fixed Deposit"",IF(REGEXMATCH(LOWER(Raw_Data!C47),""airtime""),""Airtime"",IF(REGEXMATCH(LOWER(Raw_Data!C47),""electronic money transfer levy""),""Electronic Money Trans"&"fer Levy"",IF(REGEXMATCH(LOWER(Raw_Data!C47),""transfer|trf|send""),""Transfer"",""Other"")))),""Other"")"),"Transfer") -> Transfer | E41: 1000 | F41: 0 | G41: =IF(E41 <> 0,"Withdrawal","Deposit") -> Withdrawal | H41: =TEXT(Raw_Data!A47,"hh:mm:ss") -> 13:56:52 | I41: =IF(E41<> 0,E41,F41) -> 1000
A42: =Raw_Data!A48 -> 06 Jan 2025 18:18:37 | B42: =TEXT(A42,"MMMM") -> January | C42: =MONTH(A42) -> 1 | D42: =IFERROR(__xludf.DUMMYFUNCTION("IFERROR(IF(REGEXMATCH(LOWER(Raw_Data!C48),""fixed deposit|owealth|savings|target""),""Fixed Deposit"",IF(REGEXMATCH(LOWER(Raw_Data!C48),""airtime""),""Airtime"",IF(REGEXMATCH(LOWER(Raw_Data!C48),""electronic money transfer levy""),""Electronic Money Trans"&"fer Levy"",IF(REGEXMATCH(LOWER(Raw_Data!C48),""transfer|trf|send""),""Transfer"",""Other"")))),""Other"")"),"Transfer") -> Transfer | E42: 0 | F42: 1000 | G42: =IF(E42 <> 0,"Withdrawal","Deposit") -> Deposit | H42: =TEXT(Raw_Data!A48,"hh:mm:ss") -> 18:18:37 | I42: =IF(E42<> 0,E42,F42) -> 1000
A43: =Raw_Data!A49 -> 06 Jan 2025 22:01:57 | B43: =TEXT(A43,"MMMM") -> January | C43: =MONTH(A43) -> 1 | D43: =IFERROR(__xludf.DUMMYFUNCTION("IFERROR(IF(REGEXMATCH(LOWER(Raw_Data!C49),""fixed deposit|owealth|savings|target""),""Fixed Deposit"",IF(REGEXMATCH(LOWER(Raw_Data!C49),""airtime""),""Airtime"",IF(REGEXMATCH(LOWER(Raw_Data!C49),""electronic money transfer levy""),""Electronic Money Trans"&"fer Levy"",IF(REGEXMATCH(LOWER(Raw_Data!C49),""transfer|trf|send""),""Transfer"",""Other"")))),""Other"")"),"Transfer") -> Transfer | E43: 1300 | F43: 0 | G43: =IF(E43 <> 0,"Withdrawal","Deposit") -> Withdrawal | H43: =TEXT(Raw_Data!A49,"hh:mm:ss") -> 22:01:57 | I43: =IF(E43<> 0,E43,F43) -> 1300
A44: =Raw_Data!A50 -> 07 Jan 2025 04:35:11 | B44: =TEXT(A44,"MMMM") -> January | C44: =MONTH(A44) -> 1 | D44: =IFERROR(__xludf.DUMMYFUNCTION("IFERROR(IF(REGEXMATCH(LOWER(Raw_Data!C50),""fixed deposit|owealth|savings|target""),""Fixed Deposit"",IF(REGEXMATCH(LOWER(Raw_Data!C50),""airtime""),""Airtime"",IF(REGEXMATCH(LOWER(Raw_Data!C50),""electronic money transfer levy""),""Electronic Money Trans"&"fer Levy"",IF(REGEXMATCH(LOWER(Raw_Data!C50),""transfer|trf|send""),""Transfer"",""Other"")))),""Other"")"),"Transfer") -> Transfer | E44: 0 | F44: 410520 | G44: =IF(E44 <> 0,"Withdrawal","Deposit") -> Deposit | H44: =TEXT(Raw_Data!A50,"hh:mm:ss") -> 04:35:11 | I44: =IF(E44<> 0,E44,F44) -> 410520
A45: =Raw_Data!A51 -> 07 Jan 2025 04:35:17 | B45: =TEXT(A45,"MMMM") -> January | C45: =MONTH(A45) -> 1 | D45: =IFERROR(__xludf.DUMMYFUNCTION("IFERROR(IF(REGEXMATCH(LOWER(Raw_Data!C51),""fixed deposit|owealth|savings|target""),""Fixed Deposit"",IF(REGEXMATCH(LOWER(Raw_Data!C51),""airtime""),""Airtime"",IF(REGEXMATCH(LOWER(Raw_Data!C51),""electronic money transfer levy""),""Electronic Money Trans"&"fer Levy"",IF(REGEXMATCH(LOWER(Raw_Data!C51),""transfer|trf|send""),""Transfer"",""Other"")))),""Other"")"),"Electronic Money Transfer Levy") -> Electronic Money Transfer Levy | E45: 50 | F45: 0 | G45: =IF(E45 <> 0,"Withdrawal","Deposit") -> Withdrawal | H45: =TEXT(Raw_Data!A51,"hh:mm:ss") -> 04:35:17 | I45: =IF(E45<> 0,E45,F45) -> 50
A46: =Raw_Data!A52 -> 07 Jan 2025 04:37:09 | B46: =TEXT(A46,"MMMM") -> January | C46: =MONTH(A46) -> 1 | D46: =IFERROR(__xludf.DUMMYFUNCTION("IFERROR(IF(REGEXMATCH(LOWER(Raw_Data!C52),""fixed deposit|owealth|savings|target""),""Fixed Deposit"",IF(REGEXMATCH(LOWER(Raw_Data!C52),""airtime""),""Airtime"",IF(REGEXMATCH(LOWER(Raw_Data!C52),""electronic money transfer levy""),""Electronic Money Trans"&"fer Levy"",IF(REGEXMATCH(LOWER(Raw_Data!C52),""transfer|trf|send""),""Transfer"",""Other"")))),""Other"")"),"Transfer") -> Transfer | E46: 100000 | F46: 0 | G46: =IF(E46 <> 0,"Withdrawal","Deposit") -> Withdrawal | H46: =TEXT(Raw_Data!A52,"hh:mm:ss") -> 04:37:09 | I46: =IF(E46<> 0,E46,F46) -> 100000
A47: =Raw_Data!A53 -> 07 Jan 2025 04:38:28 | B47: =TEXT(A47,"MMMM") -> January | C47: =MONTH(A47) -> 1 | D47: =IFERROR(__xludf.DUMMYFUNCTION("IFERROR(IF(REGEXMATCH(LOWER(Raw_Data!C53),""fixed deposit|owealth|savings|target""),""Fixed Deposit"",IF(REGEXMATCH(LOWER(Raw_Data!C53),""airtime""),""Airtime"",IF(REGEXMATCH(LOWER(Raw_Data!C53),""electronic money transfer levy""),""Electronic Money Trans"&"fer Levy"",IF(REGEXMATCH(LOWER(Raw_Data!C53),""transfer|trf|send""),""Transfer"",""Other"")))),""Other"")"),"Transfer") -> Transfer | E47: 95000 | F47: 0 | G47: =IF(E47 <> 0,"Withdrawal","Deposit") -> Withdrawal | H47: =TEXT(Raw_Data!A53,"hh:mm:ss") -> 04:38:28 | I47: =IF(E47<> 0,E47,F47) -> 95000
A48: =Raw_Data!A54 -> 07 Jan 2025 04:41:12 | B48: =TEXT(A48,"MMMM") -> January | C48: =MONTH(A48) -> 1 | D48: =IFERROR(__xludf.DUMMYFUNCTION("IFERROR(IF(REGEXMATCH(LOWER(Raw_Data!C54),""fixed deposit|owealth|savings|target""),""Fixed Deposit"",IF(REGEXMATCH(LOWER(Raw_Data!C54),""airtime""),""Airtime"",IF(REGEXMATCH(LOWER(Raw_Data!C54),""electronic money transfer levy""),""Electronic Money Trans"&"fer Levy"",IF(REGEXMATCH(LOWER(Raw_Data!C54),""transfer|trf|send""),""Transfer"",""Other"")))),""Other"")"),"Airtime") -> Airtime | E48: 12500 | F48: 0 | G48: =IF(E48 <> 0,"Withdrawal","Deposit") -> Withdrawal | H48: =TEXT(Raw_Data!A54,"hh:mm:ss") -> 04:41:12 | I48: =IF(E48<> 0,E48,F48) -> 12500
A49: =Raw_Data!A55 -> 07 Jan 2025 04:44:28 | B49: =TEXT(A49,"MMMM") -> January | C49: =MONTH(A49) -> 1 | D49: =IFERROR(__xludf.DUMMYFUNCTION("IFERROR(IF(REGEXMATCH(LOWER(Raw_Data!C55),""fixed deposit|owealth|savings|target""),""Fixed Deposit"",IF(REGEXMATCH(LOWER(Raw_Data!C55),""airtime""),""Airtime"",IF(REGEXMATCH(LOWER(Raw_Data!C55),""electronic money transfer levy""),""Electronic Money Trans"&"fer Levy"",IF(REGEXMATCH(LOWER(Raw_Data!C55),""transfer|trf|send""),""Transfer"",""Other"")))),""Other"")"),"Transfer") -> Transfer | E49: 50000 | F49: 0 | G49: =IF(E49 <> 0,"Withdrawal","Deposit") -> Withdrawal | H49: =TEXT(Raw_Data!A55,"hh:mm:ss") -> 04:44:28 | I49: =IF(E49<> 0,E49,F49) -> 50000
A50: =Raw_Data!A56 -> 07 Jan 2025 04:45:33 | B50: =TEXT(A50,"MMMM") -> January | C50: =MONTH(A50) -> 1 | D50: =IFERROR(__xludf.DUMMYFUNCTION("IFERROR(IF(REGEXMATCH(LOWER(Raw_Data!C56),""fixed deposit|owealth|savings|target""),""Fixed Deposit"",IF(REGEXMATCH(LOWER(Raw_Data!C56),""airtime""),""Airtime"",IF(REGEXMATCH(LOWER(Raw_Data!C56),""electronic money transfer levy""),""Electronic Money Trans"&"fer Levy"",IF(REGEXMATCH(LOWER(Raw_Data!C56),""transfer|trf|send""),""Transfer"",""Other"")))),""Other"")"),"Transfer") -> Transfer | E50: 0 | F50: 30000 | G50: =IF(E50 <> 0,"Withdrawal","Deposit") -> Deposit | H50: =TEXT(Raw_Data!A56,"hh:mm:ss") -> 04:45:33 | I50: =IF(E50<> 0,E50,F50) -> 30000
A51: =Raw_Data!A57 -> 07 Jan 2025 04:45:41 | B51: =TEXT(A51,"MMMM") -> January | C51: =MONTH(A51) -> 1 | D51: =IFERROR(__xludf.DUMMYFUNCTION("IFERROR(IF(REGEXMATCH(LOWER(Raw_Data!C57),""fixed deposit|owealth|savings|target""),""Fixed Deposit"",IF(REGEXMATCH(LOWER(Raw_Data!C57),""airtime""),""Airtime"",IF(REGEXMATCH(LOWER(Raw_Data!C57),""electronic money transfer levy""),""Electronic Money Trans"&"fer Levy"",IF(REGEXMATCH(LOWER(Raw_Data!C57),""transfer|trf|send""),""Transfer"",""Other"")))),""Other"")"),"Electronic Money Transfer Levy") -> Electronic Money Transfer Levy | E51: 50 | F51: 0 | G51: =IF(E51 <> 0,"Withdrawal","Deposit") -> Withdrawal | H51: =TEXT(Raw_Data!A57,"hh:mm:ss") -> 04:45:41 | I51: =IF(E51<> 0,E51,F51) -> 50
A52: =Raw_Data!A58 -> 07 Jan 2025 04:47:16 | B52: =TEXT(A52,"MMMM") -> January | C52: =MONTH(A52) -> 1 | D52: =IFERROR(__xludf.DUMMYFUNCTION("IFERROR(IF(REGEXMATCH(LOWER(Raw_Data!C58),""fixed deposit|owealth|savings|target""),""Fixed Deposit"",IF(REGEXMATCH(LOWER(Raw_Data!C58),""airtime""),""Airtime"",IF(REGEXMATCH(LOWER(Raw_Data!C58),""electronic money transfer levy""),""Electronic Money Trans"&"fer Levy"",IF(REGEXMATCH(LOWER(Raw_Data!C58),""transfer|trf|send""),""Transfer"",""Other"")))),""Other"")"),"Transfer") -> Transfer | E52: 4000 | F52: 0 | G52: =IF(E52 <> 0,"Withdrawal","Deposit") -> Withdrawal | H52: =TEXT(Raw_Data!A58,"hh:mm:ss") -> 04:47:16 | I52: =IF(E52<> 0,E52,F52) -> 4000
A53: =Raw_Data!A59 -> 07 Jan 2025 05:28:25 | B53: =TEXT(A53,"MMMM") -> January | C53: =MONTH(A53) -> 1 | D53: =IFERROR(__xludf.DUMMYFUNCTION("IFERROR(IF(REGEXMATCH(LOWER(Raw_Data!C59),""fixed deposit|owealth|savings|target""),""Fixed Deposit"",IF(REGEXMATCH(LOWER(Raw_Data!C59),""airtime""),""Airtime"",IF(REGEXMATCH(LOWER(Raw_Data!C59),""electronic money transfer levy""),""Electronic Money Trans"&"fer Levy"",IF(REGEXMATCH(LOWER(Raw_Data!C59),""transfer|trf|send""),""Transfer"",""Other"")))),""Other"")"),"Transfer") -> Transfer | E53: 10000 | F53: 0 | G53: =IF(E53 <> 0,"Withdrawal","Deposit") -> Withdrawal | H53: =TEXT(Raw_Data!A59,"hh:mm:ss") -> 05:28:25 | I53: =IF(E53<> 0,E53,F53) -> 10000
A54: =Raw_Data!A60 -> 07 Jan 2025 07:16:45 | B54: =TEXT(A54,"MMMM") -> January | C54: =MONTH(A54) -> 1 | D54: =IFERROR(__xludf.DUMMYFUNCTION("IFERROR(IF(REGEXMATCH(LOWER(Raw_Data!C60),""fixed deposit|owealth|savings|target""),""Fixed Deposit"",IF(REGEXMATCH(LOWER(Raw_Data!C60),""airtime""),""Airtime"",IF(REGEXMATCH(LOWER(Raw_Data!C60),""electronic money transfer levy""),""Electronic Money Trans"&"fer Levy"",IF(REGEXMATCH(LOWER(Raw_Data!C60),""transfer|trf|send""),""Transfer"",""Other"")))),""Other"")"),"Transfer") -> Transfer | E54: 300 | F54: 0 | G54: =IF(E54 <> 0,"Withdrawal","Deposit") -> Withdrawal | H54: =TEXT(Raw_Data!A60,"hh:mm:ss") -> 07:16:45 | I54: =IF(E54<> 0,E54,F54) -> 300
A55: =Raw_Data!A61 -> 07 Jan 2025 08:34:23 | B55: =TEXT(A55,"MMMM") -> January | C55: =MONTH(A55) -> 1 | D55: =IFERROR(__xludf.DUMMYFUNCTION("IFERROR(IF(REGEXMATCH(LOWER(Raw_Data!C61),""fixed deposit|owealth|savings|target""),""Fixed Deposit"",IF(REGEXMATCH(LOWER(Raw_Data!C61),""airtime""),""Airtime"",IF(REGEXMATCH(LOWER(Raw_Data!C61),""electronic money transfer levy""),""Electronic Money Trans"&"fer Levy"",IF(REGEXMATCH(LOWER(Raw_Data!C61),""transfer|trf|send""),""Transfer"",""Other"")))),""Other"")"),"Transfer") -> Transfer | E55: 1700 | F55: 0 | G55: =IF(E55 <> 0,"Withdrawal","Deposit") -> Withdrawal | H55: =TEXT(Raw_Data!A61,"hh:mm:ss") -> 08:34:23 | I55: =IF(E55<> 0,E55,F55) -> 1700
A56: =Raw_Data!A62 -> 07 Jan 2025 08:36:16 | B56: =TEXT(A56,"MMMM") -> January | C56: =MONTH(A56) -> 1 | D56: =IFERROR(__xludf.DUMMYFUNCTION("IFERROR(IF(REGEXMATCH(LOWER(Raw_Data!C62),""fixed deposit|owealth|savings|target""),""Fixed Deposit"",IF(REGEXMATCH(LOWER(Raw_Data!C62),""airtime""),""Airtime"",IF(REGEXMATCH(LOWER(Raw_Data!C62),""electronic money transfer levy""),""Electronic Money Trans"&"fer Levy"",IF(REGEXMATCH(LOWER(Raw_Data!C62),""transfer|trf|send""),""Transfer"",""Other"")))),""Other"")"),"Transfer") -> Transfer | E56: 200 | F56: 0 | G56: =IF(E56 <> 0,"Withdrawal","Deposit") -> Withdrawal | H56: =TEXT(Raw_Data!A62,"hh:mm:ss") -> 08:36:16 | I56: =IF(E56<> 0,E56,F56) -> 200
A57: =Raw_Data!A63 -> 07 Jan 2025 08:48:54 | B57: =TEXT(A57,"MMMM") -> January | C57: =MONTH(A57) -> 1 | D57: =IFERROR(__xludf.DUMMYFUNCTION("IFERROR(IF(REGEXMATCH(LOWER(Raw_Data!C63),""fixed deposit|owealth|savings|target""),""Fixed Deposit"",IF(REGEXMATCH(LOWER(Raw_Data!C63),""airtime""),""Airtime"",IF(REGEXMATCH(LOWER(Raw_Data!C63),""electronic money transfer levy""),""Electronic Money Trans"&"fer Levy"",IF(REGEXMATCH(LOWER(Raw_Data!C63),""transfer|trf|send""),""Transfer"",""Other"")))),""Other"")"),"Transfer") -> Transfer | E57: 0 | F57: 82051 | G57: =IF(E57 <> 0,"Withdrawal","Deposit") -> Deposit | H57: =TEXT(Raw_Data!A63,"hh:mm:ss") -> 08:48:54 | I57: =IF(E57<> 0,E57,F57) -> 82051
A58: =Raw_Data!A64 -> 07 Jan 2025 08:49:00 | B58: =TEXT(A58,"MMMM") -> January | C58: =MONTH(A58) -> 1 | D58: =IFERROR(__xludf.DUMMYFUNCTION("IFERROR(IF(REGEXMATCH(LOWER(Raw_Data!C64),""fixed deposit|owealth|savings|target""),""Fixed Deposit"",IF(REGEXMATCH(LOWER(Raw_Data!C64),""airtime""),""Airtime"",IF(REGEXMATCH(LOWER(Raw_Data!C64),""electronic money transfer levy""),""Electronic Money Trans"&"fer Levy"",IF(REGEXMATCH(LOWER(Raw_Data!C64),""transfer|trf|send""),""Transfer"",""Other"")))),""Other"")"),"Electronic Money Transfer Levy") -> Electronic Money Transfer Levy | E58: 50 | F58: 0 | G58: =IF(E58 <> 0,"Withdrawal","Deposit") -> Withdrawal | H58: =TEXT(Raw_Data!A64,"hh:mm:ss") -> 08:49:00 | I58: =IF(E58<> 0,E58,F58) -> 50
A59: =Raw_Data!A65 -> 07 Jan 2025 10:04:28 | B59: =TEXT(A59,"MMMM") -> January | C59: =MONTH(A59) -> 1 | D59: =IFERROR(__xludf.DUMMYFUNCTION("IFERROR(IF(REGEXMATCH(LOWER(Raw_Data!C65),""fixed deposit|owealth|savings|target""),""Fixed Deposit"",IF(REGEXMATCH(LOWER(Raw_Data!C65),""airtime""),""Airtime"",IF(REGEXMATCH(LOWER(Raw_Data!C65),""electronic money transfer levy""),""Electronic Money Trans"&"fer Levy"",IF(REGEXMATCH(LOWER(Raw_Data!C65),""transfer|trf|send""),""Transfer"",""Other"")))),""Other"")"),"Transfer") -> Transfer | E59: 3210 | F59: 0 | G59: =IF(E59 <> 0,"Withdrawal","Deposit") -> Withdrawal | H59: =TEXT(Raw_Data!A65,"hh:mm:ss") -> 10:04:28 | I59: =IF(E59<> 0,E59,F59) -> 3210
A60: =Raw_Data!A66 -> 07 Jan 2025 10:09:52 | B60: =TEXT(A60,"MMMM") -> January | C60: =MONTH(A60) -> 1 | D60: =IFERROR(__xludf.DUMMYFUNCTION("IFERROR(IF(REGEXMATCH(LOWER(Raw_Data!C66),""fixed deposit|owealth|savings|target""),""Fixed Deposit"",IF(REGEXMATCH(LOWER(Raw_Data!C66),""airtime""),""Airtime"",IF(REGEXMATCH(LOWER(Raw_Data!C66),""electronic money transfer levy""),""Electronic Money Trans"&"fer Levy"",IF(REGEXMATCH(LOWER(Raw_Data!C66),""transfer|trf|send""),""Transfer"",""Other"")))),""Other"")"),"Transfer") -> Transfer | E60: 2860 | F60: 0 | G60: =IF(E60 <> 0,"Withdrawal","Deposit") -> Withdrawal | H60: =TEXT(Raw_Data!A66,"hh:mm:ss") -> 10:09:52 | I60: =IF(E60<> 0,E60,F60) -> 2860
A61: =Raw_Data!A67 -> 07 Jan 2025 10:10:38 | B61: =TEXT(A61,"MMMM") -> January | C61: =MONTH(A61) -> 1 | D61: =IFERROR(__xludf.DUMMYFUNCTION("IFERROR(IF(REGEXMATCH(LOWER(Raw_Data!C67),""fixed deposit|owealth|savings|target""),""Fixed Deposit"",IF(REGEXMATCH(LOWER(Raw_Data!C67),""airtime""),""Airtime"",IF(REGEXMATCH(LOWER(Raw_Data!C67),""electronic money transfer levy""),""Electronic Money Trans"&"fer Levy"",IF(REGEXMATCH(LOWER(Raw_Data!C67),""transfer|trf|send""),""Transfer"",""Other"")))),""Other"")"),"Transfer") -> Transfer | E61: 3500 | F61: 0 | G61: =IF(E61 <> 0,"Withdrawal","Deposit") -> Withdrawal | H61: =TEXT(Raw_Data!A67,"hh:mm:ss") -> 10:10:38 | I61: =IF(E61<> 0,E61,F61) -> 3500
A62: =Raw_Data!A68 -> 07 Jan 2025 10:23:24 | B62: =TEXT(A62,"MMMM") -> January | C62: =MONTH(A62) -> 1 | D62: =IFERROR(__xludf.DUMMYFUNCTION("IFERROR(IF(REGEXMATCH(LOWER(Raw_Data!C68),""fixed deposit|owealth|savings|target""),""Fixed Deposit"",IF(REGEXMATCH(LOWER(Raw_Data!C68),""airtime""),""Airtime"",IF(REGEXMATCH(LOWER(Raw_Data!C68),""electronic money transfer levy""),""Electronic Money Trans"&"fer Levy"",IF(REGEXMATCH(LOWER(Raw_Data!C68),""transfer|trf|send""),""Transfer"",""Other"")))),""Other"")"),"Transfer") -> Transfer | E62: 6500 | F62: 0 | G62: =IF(E62 <> 0,"Withdrawal","Deposit") -> Withdrawal | H62: =TEXT(Raw_Data!A68,"hh:mm:ss") -> 10:23:24 | I62: =IF(E62<> 0,E62,F62) -> 6500
A63: =Raw_Data!A69 -> 07 Jan 2025 10:27:53 | B63: =TEXT(A63,"MMMM") -> January | C63: =MONTH(A63) -> 1 | D63: =IFERROR(__xludf.DUMMYFUNCTION("IFERROR(IF(REGEXMATCH(LOWER(Raw_Data!C69),""fixed deposit|owealth|savings|target""),""Fixed Deposit"",IF(REGEXMATCH(LOWER(Raw_Data!C69),""airtime""),""Airtime"",IF(REGEXMATCH(LOWER(Raw_Data!C69),""electronic money transfer levy""),""Electronic Money Trans"&"fer Levy"",IF(REGEXMATCH(LOWER(Raw_Data!C69),""transfer|trf|send""),""Transfer"",""Other"")))),""Other"")"),"Transfer") -> Transfer | E63: 510 | F63: 0 | G63: =IF(E63 <> 0,"Withdrawal","Deposit") -> Withdrawal | H63: =TEXT(Raw_Data!A69,"hh:mm:ss") -> 10:27:53 | I63: =IF(E63<> 0,E63,F63) -> 510
A64: =Raw_Data!A70 -> 07 Jan 2025 10:29:50 | B64: =TEXT(A64,"MMMM") -> January | C64: =MONTH(A64) -> 1 | D64: =IFERROR(__xludf.DUMMYFUNCTION("IFERROR(IF(REGEXMATCH(LOWER(Raw_Data!C70),""fixed deposit|owealth|savings|target""),""Fixed Deposit"",IF(REGEXMATCH(LOWER(Raw_Data!C70),""airtime""),""Airtime"",IF(REGEXMATCH(LOWER(Raw_Data!C70),""electronic money transfer levy""),""Electronic Money Trans"&"fer Levy"",IF(REGEXMATCH(LOWER(Raw_Data!C70),""transfer|trf|send""),""Transfer"",""Other"")))),""Other"")"),"Transfer") -> Transfer | E64: 1500 | F64: 0 | G64: =IF(E64 <> 0,"Withdrawal","Deposit") -> Withdrawal | H64: =TEXT(Raw_Data!A70,"hh:mm:ss") -> 10:29:50 | I64: =IF(E64<> 0,E64,F64) -> 1500
A65: =Raw_Data!A71 -> 07 Jan 2025 12:51:33 | B65: =TEXT(A65,"MMMM") -> January | C65: =MONTH(A65) -> 1 | D65: =IFERROR(__xludf.DUMMYFUNCTION("IFERROR(IF(REGEXMATCH(LOWER(Raw_Data!C71),""fixed deposit|owealth|savings|target""),""Fixed Deposit"",IF(REGEXMATCH(LOWER(Raw_Data!C71),""airtime""),""Airtime"",IF(REGEXMATCH(LOWER(Raw_Data!C71),""electronic money transfer levy""),""Electronic Money Trans"&"fer Levy"",IF(REGEXMATCH(LOWER(Raw_Data!C71),""transfer|trf|send""),""Transfer"",""Other"")))),""Other"")"),"Transfer") -> Transfer | E65: 4810 | F65: 0 | G65: =IF(E65 <> 0,"Withdrawal","Deposit") -> Withdrawal | H65: =TEXT(Raw_Data!A71,"hh:mm:ss") -> 12:51:33 | I65: =IF(E65<> 0,E65,F65) -> 4810
A66: =Raw_Data!A72 -> 07 Jan 2025 14:25:06 | B66: =TEXT(A66,"MMMM") -> January | C66: =MONTH(A66) -> 1 | D66: =IFERROR(__xludf.DUMMYFUNCTION("IFERROR(IF(REGEXMATCH(LOWER(Raw_Data!C72),""fixed deposit|owealth|savings|target""),""Fixed Deposit"",IF(REGEXMATCH(LOWER(Raw_Data!C72),""airtime""),""Airtime"",IF(REGEXMATCH(LOWER(Raw_Data!C72),""electronic money transfer levy""),""Electronic Money Trans"&"fer Levy"",IF(REGEXMATCH(LOWER(Raw_Data!C72),""transfer|trf|send""),""Transfer"",""Other"")))),""Other"")"),"Transfer") -> Transfer | E66: 47000 | F66: 0 | G66: =IF(E66 <> 0,"Withdrawal","Deposit") -> Withdrawal | H66: =TEXT(Raw_Data!A72,"hh:mm:ss") -> 14:25:06 | I66: =IF(E66<> 0,E66,F66) -> 47000
A67: =Raw_Data!A73 -> 07 Jan 2025 14:54:44 | B67: =TEXT(A67,"MMMM") -> January | C67: =MONTH(A67) -> 1 | D67: =IFERROR(__xludf.DUMMYFUNCTION("IFERROR(IF(REGEXMATCH(LOWER(Raw_Data!C73),""fixed deposit|owealth|savings|target""),""Fixed Deposit"",IF(REGEXMATCH(LOWER(Raw_Data!C73),""airtime""),""Airtime"",IF(REGEXMATCH(LOWER(Raw_Data!C73),""electronic money transfer levy""),""Electronic Money Trans"&"fer Levy"",IF(REGEXMATCH(LOWER(Raw_Data!C73),""transfer|trf|send""),""Transfer"",""Other"")))),""Other"")"),"Transfer") -> Transfer | E67: 13000 | F67: 0 | G67: =IF(E67 <> 0,"Withdrawal","Deposit") -> Withdrawal | H67: =TEXT(Raw_Data!A73,"hh:mm:ss") -> 14:54:44 | I67: =IF(E67<> 0,E67,F67) -> 13000
A68: =Raw_Data!A74 -> 07 Jan 2025 15:39:32 | B68: =TEXT(A68,"MMMM") -> January | C68: =MONTH(A68) -> 1 | D68: =IFERROR(__xludf.DUMMYFUNCTION("IFERROR(IF(REGEXMATCH(LOWER(Raw_Data!C74),""fixed deposit|owealth|savings|target""),""Fixed Deposit"",IF(REGEXMATCH(LOWER(Raw_Data!C74),""airtime""),""Airtime"",IF(REGEXMATCH(LOWER(Raw_Data!C74),""electronic money transfer levy""),""Electronic Money Trans"&"fer Levy"",IF(REGEXMATCH(LOWER(Raw_Data!C74),""transfer|trf|send""),""Transfer"",""Other"")))),""Other"")"),"Transfer") -> Transfer | E68: 2000 | F68: 0 | G68: =IF(E68 <> 0,"Withdrawal","Deposit") -> Withdrawal | H68: =TEXT(Raw_Data!A74,"hh:mm:ss") -> 15:39:32 | I68: =IF(E68<> 0,E68,F68) -> 2000
A69: =Raw_Data!A75 -> 07 Jan 2025 15:41:20 | B69: =TEXT(A69,"MMMM") -> January | C69: =MONTH(A69) -> 1 | D69: =IFERROR(__xludf.DUMMYFUNCTION("IFERROR(IF(REGEXMATCH(LOWER(Raw_Data!C75),""fixed deposit|owealth|savings|target""),""Fixed Deposit"",IF(REGEXMATCH(LOWER(Raw_Data!C75),""airtime""),""Airtime"",IF(REGEXMATCH(LOWER(Raw_Data!C75),""electronic money transfer levy""),""Electronic Money Trans"&"fer Levy"",IF(REGEXMATCH(LOWER(Raw_Data!C75),""transfer|trf|send""),""Transfer"",""Other"")))),""Other"")"),"Transfer") -> Transfer | E69: 2000 | F69: 0 | G69: =IF(E69 <> 0,"Withdrawal","Deposit") -> Withdrawal | H69: =TEXT(Raw_Data!A75,"hh:mm:ss") -> 15:41:20 | I69: =IF(E69<> 0,E69,F69) -> 2000
A70: =Raw_Data!A76 -> 07 Jan 2025 17:22:34 | B70: =TEXT(A70,"MMMM") -> January | C70: =MONTH(A70) -> 1 | D70: =IFERROR(__xludf.DUMMYFUNCTION("IFERROR(IF(REGEXMATCH(LOWER(Raw_Data!C76),""fixed deposit|owealth|savings|target""),""Fixed Deposit"",IF(REGEXMATCH(LOWER(Raw_Data!C76),""airtime""),""Airtime"",IF(REGEXMATCH(LOWER(Raw_Data!C76),""electronic money transfer levy""),""Electronic Money Trans"&"fer Levy"",IF(REGEXMATCH(LOWER(Raw_Data!C76),""transfer|trf|send""),""Transfer"",""Other"")))),""Other"")"),"Transfer") -> Transfer | E70: 3500 | F70: 0 | G70: =IF(E70 <> 0,"Withdrawal","Deposit") -> Withdrawal | H70: =TEXT(Raw_Data!A76,"hh:mm:ss") -> 17:22:34 | I70: =IF(E70<> 0,E70,F70) -> 3500
A71: =Raw_Data!A77 -> 07 Jan 2025 17:29:30 | B71: =TEXT(A71,"MMMM") -> January | C71: =MONTH(A71) -> 1 | D71: =IFERROR(__xludf.DUMMYFUNCTION("IFERROR(IF(REGEXMATCH(LOWER(Raw_Data!C77),""fixed deposit|owealth|savings|target""),""Fixed Deposit"",IF(REGEXMATCH(LOWER(Raw_Data!C77),""airtime""),""Airtime"",IF(REGEXMATCH(LOWER(Raw_Data!C77),""electronic money transfer levy""),""Electronic Money Trans"&"fer Levy"",IF(REGEXMATCH(LOWER(Raw_Data!C77),""transfer|trf|send""),""Transfer"",""Other"")))),""Other"")"),"Transfer") -> Transfer | E71: 3000 | F71: 0 | G71: =IF(E71 <> 0,"Withdrawal","Deposit") -> Withdrawal | H71: =TEXT(Raw_Data!A77,"hh:mm:ss") -> 17:29:30 | I71: =IF(E71<> 0,E71,F71) -> 3000
A72: =Raw_Data!A78 -> 07 Jan 2025 18:46:09 | B72: =TEXT(A72,"MMMM") -> January | C72: =MONTH(A72) -> 1 | D72: =IFERROR(__xludf.DUMMYFUNCTION("IFERROR(IF(REGEXMATCH(LOWER(Raw_Data!C78),""fixed deposit|owealth|savings|target""),""Fixed Deposit"",IF(REGEXMATCH(LOWER(Raw_Data!C78),""airtime""),""Airtime"",IF(REGEXMATCH(LOWER(Raw_Data!C78),""electronic money transfer levy""),""Electronic Money Trans"&"fer Levy"",IF(REGEXMATCH(LOWER(Raw_Data!C78),""transfer|trf|send""),""Transfer"",""Other"")))),""Other"")"),"Transfer") -> Transfer | E72: 1050 | F72: 0 | G72: =IF(E72 <> 0,"Withdrawal","Deposit") -> Withdrawal | H72: =TEXT(Raw_Data!A78,"hh:mm:ss") -> 18:46:09 | I72: =IF(E72<> 0,E72,F72) -> 1050
A73: =Raw_Data!A79 -> 07 Jan 2025 19:11:04 | B73: =TEXT(A73,"MMMM") -> January | C73: =MONTH(A73) -> 1 | D73: =IFERROR(__xludf.DUMMYFUNCTION("IFERROR(IF(REGEXMATCH(LOWER(Raw_Data!C79),""fixed deposit|owealth|savings|target""),""Fixed Deposit"",IF(REGEXMATCH(LOWER(Raw_Data!C79),""airtime""),""Airtime"",IF(REGEXMATCH(LOWER(Raw_Data!C79),""electronic money transfer levy""),""Electronic Money Trans"&"fer Levy"",IF(REGEXMATCH(LOWER(Raw_Data!C79),""transfer|trf|send""),""Transfer"",""Other"")))),""Other"")"),"Transfer") -> Transfer | E73: 5010 | F73: 0 | G73: =IF(E73 <> 0,"Withdrawal","Deposit") -> Withdrawal | H73: =TEXT(Raw_Data!A79,"hh:mm:ss") -> 19:11:04 | I73: =IF(E73<> 0,E73,F73) -> 5010
A74: =Raw_Data!A80 -> 07 Jan 2025 20:38:51 | B74: =TEXT(A74,"MMMM") -> January | C74: =MONTH(A74) -> 1 | D74: =IFERROR(__xludf.DUMMYFUNCTION("IFERROR(IF(REGEXMATCH(LOWER(Raw_Data!C80),""fixed deposit|owealth|savings|target""),""Fixed Deposit"",IF(REGEXMATCH(LOWER(Raw_Data!C80),""airtime""),""Airtime"",IF(REGEXMATCH(LOWER(Raw_Data!C80),""electronic money transfer levy""),""Electronic Money Trans"&"fer Levy"",IF(REGEXMATCH(LOWER(Raw_Data!C80),""transfer|trf|send""),""Transfer"",""Other"")))),""Other"")"),"Transfer") -> Transfer | E74: 0 | F74: 900 | G74: =IF(E74 <> 0,"Withdrawal","Deposit") -> Deposit | H74: =TEXT(Raw_Data!A80,"hh:mm:ss") -> 20:38:51 | I74: =IF(E74<> 0,E74,F74) -> 900
A75: =Raw_Data!A81 -> 07 Jan 2025 20:40:50 | B75: =TEXT(A75,"MMMM") -> January | C75: =MONTH(A75) -> 1 | D75: =IFERROR(__xludf.DUMMYFUNCTION("IFERROR(IF(REGEXMATCH(LOWER(Raw_Data!C81),""fixed deposit|owealth|savings|target""),""Fixed Deposit"",IF(REGEXMATCH(LOWER(Raw_Data!C81),""airtime""),""Airtime"",IF(REGEXMATCH(LOWER(Raw_Data!C81),""electronic money transfer levy""),""Electronic Money Trans"&"fer Levy"",IF(REGEXMATCH(LOWER(Raw_Data!C81),""transfer|trf|send""),""Transfer"",""Other"")))),""Other"")"),"Transfer") -> Transfer | E75: 1510 | F75: 0 | G75: =IF(E75 <> 0,"Withdrawal","Deposit") -> Withdrawal | H75: =TEXT(Raw_Data!A81,"hh:mm:ss") -> 20:40:50 | I75: =IF(E75<> 0,E75,F75) -> 1510
A76: =Raw_Data!A82 -> 08 Jan 2025 07:11:30 | B76: =TEXT(A76,"MMMM") -> January | C76: =MONTH(A76) -> 1 | D76: =IFERROR(__xludf.DUMMYFUNCTION("IFERROR(IF(REGEXMATCH(LOWER(Raw_Data!C82),""fixed deposit|owealth|savings|target""),""Fixed Deposit"",IF(REGEXMATCH(LOWER(Raw_Data!C82),""airtime""),""Airtime"",IF(REGEXMATCH(LOWER(Raw_Data!C82),""electronic money transfer levy""),""Electronic Money Trans"&"fer Levy"",IF(REGEXMATCH(LOWER(Raw_Data!C82),""transfer|trf|send""),""Transfer"",""Other"")))),""Other"")"),"Transfer") -> Transfer | E76: 200 | F76: 0 | G76: =IF(E76 <> 0,"Withdrawal","Deposit") -> Withdrawal | H76: =TEXT(Raw_Data!A82,"hh:mm:ss") -> 07:11:30 | I76: =IF(E76<> 0,E76,F76) -> 200
A77: =Raw_Data!A83 -> 08 Jan 2025 07:30:35 | B77: =TEXT(A77,"MMMM") -> January | C77: =MONTH(A77) -> 1 | D77: =IFERROR(__xludf.DUMMYFUNCTION("IFERROR(IF(REGEXMATCH(LOWER(Raw_Data!C83),""fixed deposit|owealth|savings|target""),""Fixed Deposit"",IF(REGEXMATCH(LOWER(Raw_Data!C83),""airtime""),""Airtime"",IF(REGEXMATCH(LOWER(Raw_Data!C83),""electronic money transfer levy""),""Electronic Money Trans"&"fer Levy"",IF(REGEXMATCH(LOWER(Raw_Data!C83),""transfer|trf|send""),""Transfer"",""Other"")))),""Other"")"),"Airtime") -> Airtime | E77: 500 | F77: 0 | G77: =IF(E77 <> 0,"Withdrawal","Deposit") -> Withdrawal | H77: =TEXT(Raw_Data!A83,"hh:mm:ss") -> 07:30:35 | I77: =IF(E77<> 0,E77,F77) -> 500
A78: =Raw_Data!A84 -> 08 Jan 2025 07:51:42 | B78: =TEXT(A78,"MMMM") -> January | C78: =MONTH(A78) -> 1 | D78: =IFERROR(__xludf.DUMMYFUNCTION("IFERROR(IF(REGEXMATCH(LOWER(Raw_Data!C84),""fixed deposit|owealth|savings|target""),""Fixed Deposit"",IF(REGEXMATCH(LOWER(Raw_Data!C84),""airtime""),""Airtime"",IF(REGEXMATCH(LOWER(Raw_Data!C84),""electronic money transfer levy""),""Electronic Money Trans"&"fer Levy"",IF(REGEXMATCH(LOWER(Raw_Data!C84),""transfer|trf|send""),""Transfer"",""Other"")))),""Other"")"),"Transfer") -> Transfer | E78: 0 | F78: 33600 | G78: =IF(E78 <> 0,"Withdrawal","Deposit") -> Deposit | H78: =TEXT(Raw_Data!A84,"hh:mm:ss") -> 07:51:42 | I78: =IF(E78<> 0,E78,F78) -> 33600
A79: =Raw_Data!A85 -> 08 Jan 2025 07:51:54 | B79: =TEXT(A79,"MMMM") -> January | C79: =MONTH(A79) -> 1 | D79: =IFERROR(__xludf.DUMMYFUNCTION("IFERROR(IF(REGEXMATCH(LOWER(Raw_Data!C85),""fixed deposit|owealth|savings|target""),""Fixed Deposit"",IF(REGEXMATCH(LOWER(Raw_Data!C85),""airtime""),""Airtime"",IF(REGEXMATCH(LOWER(Raw_Data!C85),""electronic money transfer levy""),""Electronic Money Trans"&"fer Levy"",IF(REGEXMATCH(LOWER(Raw_Data!C85),""transfer|trf|send""),""Transfer"",""Other"")))),""Other"")"),"Electronic Money Transfer Levy") -> Electronic Money Transfer Levy | E79: 50 | F79: 0 | G79: =IF(E79 <> 0,"Withdrawal","Deposit") -> Withdrawal | H79: =TEXT(Raw_Data!A85,"hh:mm:ss") -> 07:51:54 | I79: =IF(E79<> 0,E79,F79) -> 50
A80: =Raw_Data!A86 -> 08 Jan 2025 08:06:13 | B80: =TEXT(A80,"MMMM") -> January | C80: =MONTH(A80) -> 1 | D80: =IFERROR(__xludf.DUMMYFUNCTION("IFERROR(IF(REGEXMATCH(LOWER(Raw_Data!C86),""fixed deposit|owealth|savings|target""),""Fixed Deposit"",IF(REGEXMATCH(LOWER(Raw_Data!C86),""airtime""),""Airtime"",IF(REGEXMATCH(LOWER(Raw_Data!C86),""electronic money transfer levy""),""Electronic Money Trans"&"fer Levy"",IF(REGEXMATCH(LOWER(Raw_Data!C86),""transfer|trf|send""),""Transfer"",""Other"")))),""Other"")"),"Transfer") -> Transfer | E80: 33600 | F80: 0 | G80: =IF(E80 <> 0,"Withdrawal","Deposit") -> Withdrawal | H80: =TEXT(Raw_Data!A86,"hh:mm:ss") -> 08:06:13 | I80: =IF(E80<> 0,E80,F80) -> 33600
A81: =Raw_Data!A87 -> 08 Jan 2025 09:21:23 | B81: =TEXT(A81,"MMMM") -> January | C81: =MONTH(A81) -> 1 | D81: =IFERROR(__xludf.DUMMYFUNCTION("IFERROR(IF(REGEXMATCH(LOWER(Raw_Data!C87),""fixed deposit|owealth|savings|target""),""Fixed Deposit"",IF(REGEXMATCH(LOWER(Raw_Data!C87),""airtime""),""Airtime"",IF(REGEXMATCH(LOWER(Raw_Data!C87),""electronic money transfer levy""),""Electronic Money Trans"&"fer Levy"",IF(REGEXMATCH(LOWER(Raw_Data!C87),""transfer|trf|send""),""Transfer"",""Other"")))),""Other"")"),"Transfer") -> Transfer | E81: 40000 | F81: 0 | G81: =IF(E81 <> 0,"Withdrawal","Deposit") -> Withdrawal | H81: =TEXT(Raw_Data!A87,"hh:mm:ss") -> 09:21:23 | I81: =IF(E81<> 0,E81,F81) -> 40000
A82: =Raw_Data!A88 -> 08 Jan 2025 10:24:40 | B82: =TEXT(A82,"MMMM") -> January | C82: =MONTH(A82) -> 1 | D82: =IFERROR(__xludf.DUMMYFUNCTION("IFERROR(IF(REGEXMATCH(LOWER(Raw_Data!C88),""fixed deposit|owealth|savings|target""),""Fixed Deposit"",IF(REGEXMATCH(LOWER(Raw_Data!C88),""airtime""),""Airtime"",IF(REGEXMATCH(LOWER(Raw_Data!C88),""electronic money transfer levy""),""Electronic Money Trans"&"fer Levy"",IF(REGEXMATCH(LOWER(Raw_Data!C88),""transfer|trf|send""),""Transfer"",""Other"")))),""Other"")"),"Transfer") -> Transfer | E82: 3000 | F82: 0 | G82: =IF(E82 <> 0,"Withdrawal","Deposit") -> Withdrawal | H82: =TEXT(Raw_Data!A88,"hh:mm:ss") -> 10:24:40 | I82: =IF(E82<> 0,E82,F82) -> 3000
A83: =Raw_Data!A89 -> 08 Jan 2025 12:29:10 | B83: =TEXT(A83,"MMMM") -> January | C83: =MONTH(A83) -> 1 | D83: =IFERROR(__xludf.DUMMYFUNCTION("IFERROR(IF(REGEXMATCH(LOWER(Raw_Data!C89),""fixed deposit|owealth|savings|target""),""Fixed Deposit"",IF(REGEXMATCH(LOWER(Raw_Data!C89),""airtime""),""Airtime"",IF(REGEXMATCH(LOWER(Raw_Data!C89),""electronic money transfer levy""),""Electronic Money Trans"&"fer Levy"",IF(REGEXMATCH(LOWER(Raw_Data!C89),""transfer|trf|send""),""Transfer"",""Other"")))),""Other"")"),"Transfer") -> Transfer | E83: 2000 | F83: 0 | G83: =IF(E83 <> 0,"Withdrawal","Deposit") -> Withdrawal | H83: =TEXT(Raw_Data!A89,"hh:mm:ss") -> 12:29:10 | I83: =IF(E83<> 0,E83,F83) -> 2000
A84: =Raw_Data!A90 -> 08 Jan 2025 12:56:11 | B84: =TEXT(A84,"MMMM") -> January | C84: =MONTH(A84) -> 1 | D84: =IFERROR(__xludf.DUMMYFUNCTION("IFERROR(IF(REGEXMATCH(LOWER(Raw_Data!C90),""fixed deposit|owealth|savings|target""),""Fixed Deposit"",IF(REGEXMATCH(LOWER(Raw_Data!C90),""airtime""),""Airtime"",IF(REGEXMATCH(LOWER(Raw_Data!C90),""electronic money transfer levy""),""Electronic Money Trans"&"fer Levy"",IF(REGEXMATCH(LOWER(Raw_Data!C90),""transfer|trf|send""),""Transfer"",""Other"")))),""Other"")"),"Transfer") -> Transfer | E84: 1500 | F84: 0 | G84: =IF(E84 <> 0,"Withdrawal","Deposit") -> Withdrawal | H84: =TEXT(Raw_Data!A90,"hh:mm:ss") -> 12:56:11 | I84: =IF(E84<> 0,E84,F84) -> 1500
A85: =Raw_Data!A91 -> 08 Jan 2025 13:16:57 | B85: =TEXT(A85,"MMMM") -> January | C85: =MONTH(A85) -> 1 | D85: =IFERROR(__xludf.DUMMYFUNCTION("IFERROR(IF(REGEXMATCH(LOWER(Raw_Data!C91),""fixed deposit|owealth|savings|target""),""Fixed Deposit"",IF(REGEXMATCH(LOWER(Raw_Data!C91),""airtime""),""Airtime"",IF(REGEXMATCH(LOWER(Raw_Data!C91),""electronic money transfer levy""),""Electronic Money Trans"&"fer Levy"",IF(REGEXMATCH(LOWER(Raw_Data!C91),""transfer|trf|send""),""Transfer"",""Other"")))),""Other"")"),"Transfer") -> Transfer | E85: 17000 | F85: 0 | G85: =IF(E85 <> 0,"Withdrawal","Deposit") -> Withdrawal | H85: =TEXT(Raw_Data!A91,"hh:mm:ss") -> 13:16:57 | I85: =IF(E85<> 0,E85,F85) -> 17000
A86: =Raw_Data!A92 -> 08 Jan 2025 13:33:57 | B86: =TEXT(A86,"MMMM") -> January | C86: =MONTH(A86) -> 1 | D86: =IFERROR(__xludf.DUMMYFUNCTION("IFERROR(IF(REGEXMATCH(LOWER(Raw_Data!C92),""fixed deposit|owealth|savings|target""),""Fixed Deposit"",IF(REGEXMATCH(LOWER(Raw_Data!C92),""airtime""),""Airtime"",IF(REGEXMATCH(LOWER(Raw_Data!C92),""electronic money transfer levy""),""Electronic Money Trans"&"fer Levy"",IF(REGEXMATCH(LOWER(Raw_Data!C92),""transfer|trf|send""),""Transfer"",""Other"")))),""Other"")"),"Transfer") -> Transfer | E86: 2000 | F86: 0 | G86: =IF(E86 <> 0,"Withdrawal","Deposit") -> Withdrawal | H86: =TEXT(Raw_Data!A92,"hh:mm:ss") -> 13:33:57 | I86: =IF(E86<> 0,E86,F86) -> 2000
A87: =Raw_Data!A93 -> 08 Jan 2025 14:39:28 | B87: =TEXT(A87,"MMMM") -> January | C87: =MONTH(A87) -> 1 | D87: =IFERROR(__xludf.DUMMYFUNCTION("IFERROR(IF(REGEXMATCH(LOWER(Raw_Data!C93),""fixed deposit|owealth|savings|target""),""Fixed Deposit"",IF(REGEXMATCH(LOWER(Raw_Data!C93),""airtime""),""Airtime"",IF(REGEXMATCH(LOWER(Raw_Data!C93),""electronic money transfer levy""),""Electronic Money Trans"&"fer Levy"",IF(REGEXMATCH(LOWER(Raw_Data!C93),""transfer|trf|send""),""Transfer"",""Other"")))),""Other"")"),"Transfer") -> Transfer | E87: 6000 | F87: 0 | G87: =IF(E87 <> 0,"Withdrawal","Deposit") -> Withdrawal | H87: =TEXT(Raw_Data!A93,"hh:mm:ss") -> 14:39:28 | I87: =IF(E87<> 0,E87,F87) -> 6000
A88: =Raw_Data!A94 -> 08 Jan 2025 17:16:59 | B88: =TEXT(A88,"MMMM") -> January | C88: =MONTH(A88) -> 1 | D88: =IFERROR(__xludf.DUMMYFUNCTION("IFERROR(IF(REGEXMATCH(LOWER(Raw_Data!C94),""fixed deposit|owealth|savings|target""),""Fixed Deposit"",IF(REGEXMATCH(LOWER(Raw_Data!C94),""airtime""),""Airtime"",IF(REGEXMATCH(LOWER(Raw_Data!C94),""electronic money transfer levy""),""Electronic Money Trans"&"fer Levy"",IF(REGEXMATCH(LOWER(Raw_Data!C94),""transfer|trf|send""),""Transfer"",""Other"")))),""Other"")"),"Transfer") -> Transfer | E88: 5000 | F88: 0 | G88: =IF(E88 <> 0,"Withdrawal","Deposit") -> Withdrawal | H88: =TEXT(Raw_Data!A94,"hh:mm:ss") -> 17:16:59 | I88: =IF(E88<> 0,E88,F88) -> 5000
A89: =Raw_Data!A95 -> 08 Jan 2025 18:05:38 | B89: =TEXT(A89,"MMMM") -> January | C89: =MONTH(A89) -> 1 | D89: =IFERROR(__xludf.DUMMYFUNCTION("IFERROR(IF(REGEXMATCH(LOWER(Raw_Data!C95),""fixed deposit|owealth|savings|target""),""Fixed Deposit"",IF(REGEXMATCH(LOWER(Raw_Data!C95),""airtime""),""Airtime"",IF(REGEXMATCH(LOWER(Raw_Data!C95),""electronic money transfer levy""),""Electronic Money Trans"&"fer Levy"",IF(REGEXMATCH(LOWER(Raw_Data!C95),""transfer|trf|send""),""Transfer"",""Other"")))),""Other"")"),"Transfer") -> Transfer | E89: 0 | F89: 74160 | G89: =IF(E89 <> 0,"Withdrawal","Deposit") -> Deposit | H89: =TEXT(Raw_Data!A95,"hh:mm:ss") -> 18:05:38 | I89: =IF(E89<> 0,E89,F89) -> 74160
A90: =Raw_Data!A96 -> 08 Jan 2025 18:05:44 | B90: =TEXT(A90,"MMMM") -> January | C90: =MONTH(A90) -> 1 | D90: =IFERROR(__xludf.DUMMYFUNCTION("IFERROR(IF(REGEXMATCH(LOWER(Raw_Data!C96),""fixed deposit|owealth|savings|target""),""Fixed Deposit"",IF(REGEXMATCH(LOWER(Raw_Data!C96),""airtime""),""Airtime"",IF(REGEXMATCH(LOWER(Raw_Data!C96),""electronic money transfer levy""),""Electronic Money Trans"&"fer Levy"",IF(REGEXMATCH(LOWER(Raw_Data!C96),""transfer|trf|send""),""Transfer"",""Other"")))),""Other"")"),"Electronic Money Transfer Levy") -> Electronic Money Transfer Levy | E90: 50 | F90: 0 | G90: =IF(E90 <> 0,"Withdrawal","Deposit") -> Withdrawal | H90: =TEXT(Raw_Data!A96,"hh:mm:ss") -> 18:05:44 | I90: =IF(E90<> 0,E90,F90) -> 50
A91: =Raw_Data!A97 -> 08 Jan 2025 18:06:26 | B91: =TEXT(A91,"MMMM") -> January | C91: =MONTH(A91) -> 1 | D91: =IFERROR(__xludf.DUMMYFUNCTION("IFERROR(IF(REGEXMATCH(LOWER(Raw_Data!C97),""fixed deposit|owealth|savings|target""),""Fixed Deposit"",IF(REGEXMATCH(LOWER(Raw_Data!C97),""airtime""),""Airtime"",IF(REGEXMATCH(LOWER(Raw_Data!C97),""electronic money transfer levy""),""Electronic Money Trans"&"fer Levy"",IF(REGEXMATCH(LOWER(Raw_Data!C97),""transfer|trf|send""),""Transfer"",""Other"")))),""Other"")"),"Transfer") -> Transfer | E91: 10000 | F91: 0 | G91: =IF(E91 <> 0,"Withdrawal","Deposit") -> Withdrawal | H91: =TEXT(Raw_Data!A97,"hh:mm:ss") -> 18:06:26 | I91: =IF(E91<> 0,E91,F91) -> 10000
A92: =Raw_Data!A98 -> 08 Jan 2025 18:06:53 | B92: =TEXT(A92,"MMMM") -> January | C92: =MONTH(A92) -> 1 | D92: =IFERROR(__xludf.DUMMYFUNCTION("IFERROR(IF(REGEXMATCH(LOWER(Raw_Data!C98),""fixed deposit|owealth|savings|target""),""Fixed Deposit"",IF(REGEXMATCH(LOWER(Raw_Data!C98),""airtime""),""Airtime"",IF(REGEXMATCH(LOWER(Raw_Data!C98),""electronic money transfer levy""),""Electronic Money Trans"&"fer Levy"",IF(REGEXMATCH(LOWER(Raw_Data!C98),""transfer|trf|send""),""Transfer"",""Other"")))),""Other"")"),"Transfer") -> Transfer | E92: 64000 | F92: 0 | G92: =IF(E92 <> 0,"Withdrawal","Deposit") -> Withdrawal | H92: =TEXT(Raw_Data!A98,"hh:mm:ss") -> 18:06:53 | I92: =IF(E92<> 0,E92,F92) -> 64000
A93: =Raw_Data!A99 -> 08 Jan 2025 19:07:31 | B93: =TEXT(A93,"MMMM") -> January | C93: =MONTH(A93) -> 1 | D93: =IFERROR(__xludf.DUMMYFUNCTION("IFERROR(IF(REGEXMATCH(LOWER(Raw_Data!C99),""fixed deposit|owealth|savings|target""),""Fixed Deposit"",IF(REGEXMATCH(LOWER(Raw_Data!C99),""airtime""),""Airtime"",IF(REGEXMATCH(LOWER(Raw_Data!C99),""electronic money transfer levy""),""Electronic Money Trans"&"fer Levy"",IF(REGEXMATCH(LOWER(Raw_Data!C99),""transfer|trf|send""),""Transfer"",""Other"")))),""Other"")"),"Transfer") -> Transfer | E93: 3010 | F93: 0 | G93: =IF(E93 <> 0,"Withdrawal","Deposit") -> Withdrawal | H93: =TEXT(Raw_Data!A99,"hh:mm:ss") -> 19:07:31 | I93: =IF(E93<> 0,E93,F93) -> 3010
A94: =Raw_Data!A100 -> 08 Jan 2025 19:24:31 | B94: =TEXT(A94,"MMMM") -> January | C94: =MONTH(A94) -> 1 | D94: =IFERROR(__xludf.DUMMYFUNCTION("IFERROR(IF(REGEXMATCH(LOWER(Raw_Data!C100),""fixed deposit|owealth|savings|target""),""Fixed Deposit"",IF(REGEXMATCH(LOWER(Raw_Data!C100),""airtime""),""Airtime"",IF(REGEXMATCH(LOWER(Raw_Data!C100),""electronic money transfer levy""),""Electronic Money Tr"&"ansfer Levy"",IF(REGEXMATCH(LOWER(Raw_Data!C100),""transfer|trf|send""),""Transfer"",""Other"")))),""Other"")"),"Transfer") -> Transfer | E94: 5000 | F94: 0 | G94: =IF(E94 <> 0,"Withdrawal","Deposit") -> Withdrawal | H94: =TEXT(Raw_Data!A100,"hh:mm:ss") -> 19:24:31 | I94: =IF(E94<> 0,E94,F94) -> 5000
A95: =Raw_Data!A101 -> 08 Jan 2025 19:26:10 | B95: =TEXT(A95,"MMMM") -> January | C95: =MONTH(A95) -> 1 | D95: =IFERROR(__xludf.DUMMYFUNCTION("IFERROR(IF(REGEXMATCH(LOWER(Raw_Data!C101),""fixed deposit|owealth|savings|target""),""Fixed Deposit"",IF(REGEXMATCH(LOWER(Raw_Data!C101),""airtime""),""Airtime"",IF(REGEXMATCH(LOWER(Raw_Data!C101),""electronic money transfer levy""),""Electronic Money Tr"&"ansfer Levy"",IF(REGEXMATCH(LOWER(Raw_Data!C101),""transfer|trf|send""),""Transfer"",""Other"")))),""Other"")"),"Transfer") -> Transfer | E95: 1000 | F95: 0 | G95: =IF(E95 <> 0,"Withdrawal","Deposit") -> Withdrawal | H95: =TEXT(Raw_Data!A101,"hh:mm:ss") -> 19:26:10 | I95: =IF(E95<> 0,E95,F95) -> 1000
A96: =Raw_Data!A102 -> 09 Jan 2025 07:56:44 | B96: =TEXT(A96,"MMMM") -> January | C96: =MONTH(A96) -> 1 | D96: =IFERROR(__xludf.DUMMYFUNCTION("IFERROR(IF(REGEXMATCH(LOWER(Raw_Data!C102),""fixed deposit|owealth|savings|target""),""Fixed Deposit"",IF(REGEXMATCH(LOWER(Raw_Data!C102),""airtime""),""Airtime"",IF(REGEXMATCH(LOWER(Raw_Data!C102),""electronic money transfer levy""),""Electronic Money Tr"&"ansfer Levy"",IF(REGEXMATCH(LOWER(Raw_Data!C102),""transfer|trf|send""),""Transfer"",""Other"")))),""Other"")"),"Transfer") -> Transfer | E96: 2000 | F96: 0 | G96: =IF(E96 <> 0,"Withdrawal","Deposit") -> Withdrawal | H96: =TEXT(Raw_Data!A102,"hh:mm:ss") -> 07:56:44 | I96: =IF(E96<> 0,E96,F96) -> 2000
A97: =Raw_Data!A103 -> 09 Jan 2025 08:05:09 | B97: =TEXT(A97,"MMMM") -> January | C97: =MONTH(A97) -> 1 | D97: =IFERROR(__xludf.DUMMYFUNCTION("IFERROR(IF(REGEXMATCH(LOWER(Raw_Data!C103),""fixed deposit|owealth|savings|target""),""Fixed Deposit"",IF(REGEXMATCH(LOWER(Raw_Data!C103),""airtime""),""Airtime"",IF(REGEXMATCH(LOWER(Raw_Data!C103),""electronic money transfer levy""),""Electronic Money Tr"&"ansfer Levy"",IF(REGEXMATCH(LOWER(Raw_Data!C103),""transfer|trf|send""),""Transfer"",""Other"")))),""Other"")"),"Transfer") -> Transfer | E97: 1050 | F97: 0 | G97: =IF(E97 <> 0,"Withdrawal","Deposit") -> Withdrawal | H97: =TEXT(Raw_Data!A103,"hh:mm:ss") -> 08:05:09 | I97: =IF(E97<> 0,E97,F97) -> 1050
A98: =Raw_Data!A104 -> 09 Jan 2025 09:47:00 | B98: =TEXT(A98,"MMMM") -> January | C98: =MONTH(A98) -> 1 | D98: =IFERROR(__xludf.DUMMYFUNCTION("IFERROR(IF(REGEXMATCH(LOWER(Raw_Data!C104),""fixed deposit|owealth|savings|target""),""Fixed Deposit"",IF(REGEXMATCH(LOWER(Raw_Data!C104),""airtime""),""Airtime"",IF(REGEXMATCH(LOWER(Raw_Data!C104),""electronic money transfer levy""),""Electronic Money Tr"&"ansfer Levy"",IF(REGEXMATCH(LOWER(Raw_Data!C104),""transfer|trf|send""),""Transfer"",""Other"")))),""Other"")"),"Transfer") -> Transfer | E98: 400 | F98: 0 | G98: =IF(E98 <> 0,"Withdrawal","Deposit") -> Withdrawal | H98: =TEXT(Raw_Data!A104,"hh:mm:ss") -> 09:47:00 | I98: =IF(E98<> 0,E98,F98) -> 400
A99: =Raw_Data!A105 -> 09 Jan 2025 11:16:57 | B99: =TEXT(A99,"MMMM") -> January | C99: =MONTH(A99) -> 1 | D99: =IFERROR(__xludf.DUMMYFUNCTION("IFERROR(IF(REGEXMATCH(LOWER(Raw_Data!C105),""fixed deposit|owealth|savings|target""),""Fixed Deposit"",IF(REGEXMATCH(LOWER(Raw_Data!C105),""airtime""),""Airtime"",IF(REGEXMATCH(LOWER(Raw_Data!C105),""electronic money transfer levy""),""Electronic Money Tr"&"ansfer Levy"",IF(REGEXMATCH(LOWER(Raw_Data!C105),""transfer|trf|send""),""Transfer"",""Other"")))),""Other"")"),"Transfer") -> Transfer | E99: 3000 | F99: 0 | G99: =IF(E99 <> 0,"Withdrawal","Deposit") -> Withdrawal | H99: =TEXT(Raw_Data!A105,"hh:mm:ss") -> 11:16:57 | I99: =IF(E99<> 0,E99,F99) -> 3000
A100: =Raw_Data!A106 -> 09 Jan 2025 12:07:10 | B100: =TEXT(A100,"MMMM") -> January | C100: =MONTH(A100) -> 1 | D100: =IFERROR(__xludf.DUMMYFUNCTION("IFERROR(IF(REGEXMATCH(LOWER(Raw_Data!C106),""fixed deposit|owealth|savings|target""),""Fixed Deposit"",IF(REGEXMATCH(LOWER(Raw_Data!C106),""airtime""),""Airtime"",IF(REGEXMATCH(LOWER(Raw_Data!C106),""electronic money transfer levy""),""Electronic Money Tr"&"ansfer Levy"",IF(REGEXMATCH(LOWER(Raw_Data!C106),""transfer|trf|send""),""Transfer"",""Other"")))),""Other"")"),"Transfer") -> Transfer | E100: 300 | F100: 0 | G100: =IF(E100 <> 0,"Withdrawal","Deposit") -> Withdrawal | H100: =TEXT(Raw_Data!A106,"hh:mm:ss") -> 12:07:10 | I100: =IF(E100<> 0,E100,F100) -> 300
...

Sheet Pivot_Monthly

Sheet Monthly_Summary
A1: Months | B1: Total Deposits | C1: Total Withdrawals | D1: Net_Cash_Flow
A2: January | B2: =SUMIFS(Cleaned_Data!F:F,Cleaned_Data!B:B, A2,Cleaned_Data!G:G,"Deposit") -> 1063571 | C2: =SUMIFS(Cleaned_Data!E:E,Cleaned_Data!B:B, A2,Cleaned_Data!G:G,"Withdrawal") -> 1065070.9 | D2: =B2 - C2 -> -1499.92 | H2: Category Total Amount | I2: Amount
A3: February | B3: =SUMIFS(Cleaned_Data!F:F,Cleaned_Data!B:B, A3,Cleaned_Data!G:G,"Deposit") -> 507767 | C3: =SUMIFS(Cleaned_Data!E:E,Cleaned_Data!B:B, A3,Cleaned_Data!G:G,"Withdrawal") -> 505090 | D3: =B3 - C3 -> 2677 | H3: Transfer | I3: =SUMIFS(Cleaned_Data!I:I, Cleaned_Data!D:D, H3) -> 11221863
A4: March | B4: =SUMIFS(Cleaned_Data!F:F,Cleaned_Data!B:B, A4,Cleaned_Data!G:G,"Deposit") -> 461251 | C4: =SUMIFS(Cleaned_Data!E:E,Cleaned_Data!B:B, A4,Cleaned_Data!G:G,"Withdrawal") -> 458331 | D4: =B4 - C4 -> 2920 | H4: Airtime | I4: =SUMIFS(Cleaned_Data!I:I, Cleaned_Data!D:D, H4) -> 245113.65
A5: April | B5: =SUMIFS(Cleaned_Data!F:F,Cleaned_Data!B:B, A5,Cleaned_Data!G:G,"Deposit") -> 1558832 | C5: =SUMIFS(Cleaned_Data!E:E,Cleaned_Data!B:B, A5,Cleaned_Data!G:G,"Withdrawal") -> 1562230 | D5: =B5 - C5 -> -3398 | H5: Fixed Deposit | I5: =SUMIFS(Cleaned_Data!I:I, Cleaned_Data!D:D, H5) -> 124064.81
A6: May | B6: =SUMIFS(Cleaned_Data!F:F,Cleaned_Data!B:B, A6,Cleaned_Data!G:G,"Deposit") -> 364162.19 | C6: =SUMIFS(Cleaned_Data!E:E,Cleaned_Data!B:B, A6,Cleaned_Data!G:G,"Withdrawal") -> 365960 | D6: =B6 - C6 -> -1797.81 | H6: Electronic Money Transfer Levy | I6: =SUMIFS(Cleaned_Data!I:I, Cleaned_Data!D:D, H6) -> 4750
A7: June | B7: =SUMIFS(Cleaned_Data!F:F,Cleaned_Data!B:B, A7,Cleaned_Data!G:G,"Deposit") -> 499866 | C7: =SUMIFS(Cleaned_Data!E:E,Cleaned_Data!B:B, A7,Cleaned_Data!G:G,"Withdrawal") -> 494279.9 | D7: =B7 - C7 -> 5586.1
A8: July | B8: =SUMIFS(Cleaned_Data!F:F,Cleaned_Data!B:B, A8,Cleaned_Data!G:G,"Deposit") -> 105900 | C8: =SUMIFS(Cleaned_Data!E:E,Cleaned_Data!B:B, A8,Cleaned_Data!G:G,"Withdrawal") -> 111794 | D8: =B8 - C8 -> -5894
A9: August | B9: =SUMIFS(Cleaned_Data!F:F,Cleaned_Data!B:B, A9,Cleaned_Data!G:G,"Deposit") -> 587483 | C9: =SUMIFS(Cleaned_Data!E:E,Cleaned_Data!B:B, A9,Cleaned_Data!G:G,"Withdrawal") -> 583402 | D9: =B9 - C9 -> 4081
A10: September | B10: =SUMIFS(Cleaned_Data!F:F,Cleaned_Data!B:B, A10,Cleaned_Data!G:G,"Deposit") -> 242371.5 | C10: =SUMIFS(Cleaned_Data!E:E,Cleaned_Data!B:B, A10,Cleaned_Data!G:G,"Withdrawal") -> 230945 | D10: =B10 - C10 -> 11426.5
A11: October | B11: =SUMIFS(Cleaned_Data!F:F,Cleaned_Data!B:B, A11,Cleaned_Data!G:G,"Deposit") -> 155850 | C11: =SUMIFS(Cleaned_Data!E:E,Cleaned_Data!B:B, A11,Cleaned_Data!G:G,"Withdrawal") -> 164052.65 | D11: =B11 - C11 -> -8202.65
A12: November | B12: =SUMIFS(Cleaned_Data!F:F,Cleaned_Data!B:B, A12,Cleaned_Data!G:G,"Deposit") -> 199502.62 | C12: =SUMIFS(Cleaned_Data!E:E,Cleaned_Data!B:B, A12,Cleaned_Data!G:G,"Withdrawal") -> 206950 | D12: =B12 - C12 -> -7447.38
A13: December | B13: =SUMIFS(Cleaned_Data!F:F,Cleaned_Data!B:B, A13,Cleaned_Data!G:G,"Deposit") -> 182529 | C13: =SUMIFS(Cleaned_Data!E:E,Cleaned_Data!B:B, A13,Cleaned_Data!G:G,"Withdrawal") -> 176248 | D13: =B13 - C13 -> 6281

Sheet Sheet4
A1: Personal Finance Analysis Transaction Charts
